Workbook

Sheet data
A1: Age | B1: Age-group | C1: Attrition | D1: BusinessTravel | E1: Department | F1: DistanceFromHome | G1: DistanceFromHome | H1: Education | I1: Education | J1: EducationField | K1: EnvironmentSatisfaction | L1: EnvironmentSatisfaction | M1: Gender | N1: JobInvolvement | O1: JobInvolvement | P1: JobLevel | Q1: JobLevel | R1: JobRole | S1: JobSatisfaction | T1: JobSatisfaction | U1: MaritalStatus | V1: MonthlyIncome | W1: NumCompaniesWorked | X1: NumCompaniesWorked | Y1: OverTime | Z1: PercentSalaryHike | AA1: PercentSalaryHike | AB1: PerformanceRating | AC1: PerformanceRating | AD1: RelationshipSatisfaction | AE1: RelationshipSatisfaction | AG1: StockOptionLevel | AH1: StockOptionLevel | AI1: TotalWorkingYears | AJ1: TotalWorkingYears | AK1: TrainingTimesLastYear | AL1: TrainingTimesLastYear | AM1: WorkLifeBalance | AN1: WorkLifeBalance | AO1: YearsAtCompany | AP1: YearsAtCompany | AQ1: YearsInCurrentRole | AR1: YearsInCurrentRole | AS1: YearsSinceLastPromotion | AT1: YearsSinceLastPromotion | AU1: YearsWithCurrManager | AV1: YearsWithCurrManager
A2: 27 | B2: {=_xlfn.IFS(A2<=25,"early career",A2<=35,"mid career",A2<=45,"experienced",A2>=46,"senior")} -> mid career | C2: No | D2: Travel_Rarely | E2: Research & Development | F2: 2 | G2: {=_xlfn.IFS(F2<=5,"very near",F2<=10,"near",F2<=20,"moderate",F2<=29,"far")} -> very near | H2: 1 | I2: {=_xlfn.IFS(H2=1,"Below College",H2= 2,"College",H2= 3,"Bachelor",H2= 4,"Master",H2= 5,"Doctor")} -> Below College | J2: Medical | K2: 1 | L2: {=_xlfn.IFS(K2=1,"low",K2=2,"medium",K2=3,"high",K2=4,"very high")} -> low | M2: Male | N2: 3 | O2: {=_xlfn.IFS(N2=1,"low",N2=2,"medium",N2=3,"high",N2=4,"very high")} -> high | P2: 1 | Q2: {=_xlfn.IFS(P2=1,"junior",P2=2,"mid level",P2=3,"senior",P2=4,"lead",P2=5,"executive")} -> junior | R2: Laboratory Technician | S2: 2 | T2: {=_xlfn.IFS(S2=1,"low",S2=2,"medium",S2=3,"high",S2=4,"very high")} -> medium | U2: Married | V2: 3468 | W2: 9 | X2: {=_xlfn.IFS(W2=0,"fresher",W2<=3,"stable",W2<=6,"moderate hopper",W2<=9,"frequent hopper")} -> frequent hopper | Y2: No | Z2: 12 | AA2: {=_xlfn.IFS(Z2<=14,"low hike",Z2<=18,"moderate hike",Z2<=22,"good hike",Z2<=25,"high hike")} -> low hike | AB2: 3 | AC2: {=_xlfn.IFS(AB2=1,"low",AB2=2,"good",AB2=3,"excellent",AB2=4,"outstanding")} -> excellent | AD2: 4 | AE2: {=_xlfn.IFS(AD2=1,"low",AD2=2,"medium",AD2=3,"high",AD2=4,"very high")} -> very high | AG2: 1 | AH2: {=_xlfn.IFS(AG2=0,"no stock options",AG2=2,"medium",AG2=3,"high",AG2=1,"low")} -> low | AI2: 6 | AJ2: {=_xlfn.IFS(AI2<=2,"fresher",AI2<=7,"early career",AI2<=15,"mid career",AI2<=25,"experienced",AI2>=26,"expert")} -> early career | AK2: 3 | AL2: {=_xlfn.IFS(AK2=0,"no training",AK2<=2,"low",AK2<=4,"moderate",AK2<=6,"high")} -> moderate | AM2: 3 | AN2: {=_xlfn.IFS(AM2=1,"low",AM2=2,"medium",AM2=3,"high",AM2=4,"very high")} -> high | AO2: 2 | AP2: {=_xlfn.IFS(AO2<=1,"new",AO2<=5,"early tenure",AO2<=10,"established",AO2<=20,"loyal",AO2>=21,"long term")} -> early tenure | AQ2: 2 | AR2: {=_xlfn.IFS(AQ2<=1,"new",AQ2<=4,"settling",AQ2<=7,"established",AQ2<=12,"stagnant risk",AQ2>12,"highly stagnant")} -> settling | AS2: 2 | AT2: {=_xlfn.IFS(AS2<=1,"recently promoted",AS2<=3,"due soon",AS2<=6,"over due",AS2>=7,"critically overdue")} -> due soon | AU2: 2 | AV2: {=_xlfn.IFS(AU2<=1,"new under manager",AU2<=4,"settling",AU2<=8,"established",AU2>=9,"long term")} -> settling
A3: 35 | B3: {=_xlfn.IFS(A3<=25,"early career",A3<=35,"mid career",A3<=45,"experienced",A3>=46,"senior")} -> mid career | C3: No | D3: Travel_Rarely | E3: Research & Development | F3: 16 | G3: {=_xlfn.IFS(F3<=5,"very near",F3<=10,"near",F3<=20,"moderate",F3<=29,"far")} -> moderate | H3: 3 | I3: {=_xlfn.IFS(H3=1,"Below College",H3= 2,"College",H3= 3,"Bachelor",H3= 4,"Master",H3= 5,"Doctor")} -> Bachelor | J3: Medical | K3: 1 | L3: {=_xlfn.IFS(K3=1,"low",K3=2,"medium",K3=3,"high",K3=4,"very high")} -> low | M3: Male | N3: 4 | O3: {=_xlfn.IFS(N3=1,"low",N3=2,"medium",N3=3,"high",N3=4,"very high")} -> very high | P3: 1 | Q3: {=_xlfn.IFS(P3=1,"junior",P3=2,"mid level",P3=3,"senior",P3=4,"lead",P3=5,"executive")} -> junior | R3: Laboratory Technician | S3: 2 | T3: {=_xlfn.IFS(S3=1,"low",S3=2,"medium",S3=3,"high",S3=4,"very high")} -> medium | U3: Married | V3: 2426 | W3: 0 | X3: {=_xlfn.IFS(W3=0,"fresher",W3<=3,"stable",W3<=6,"moderate hopper",W3<=9,"frequent hopper")} -> fresher | Y3: No | Z3: 13 | AA3: {=_xlfn.IFS(Z3<=14,"low hike",Z3<=18,"moderate hike",Z3<=22,"good hike",Z3<=25,"high hike")} -> low hike | AB3: 3 | AC3: {=_xlfn.IFS(AB3=1,"low",AB3=2,"good",AB3=3,"excellent",AB3=4,"outstanding")} -> excellent | AD3: 3 | AE3: {=_xlfn.IFS(AD3=1,"low",AD3=2,"medium",AD3=3,"high",AD3=4,"very high")} -> high | AG3: 1 | AH3: {=_xlfn.IFS(AG3=0,"no stock options",AG3=2,"medium",AG3=3,"high",AG3=1,"low")} -> low | AI3: 6 | AJ3: {=_xlfn.IFS(AI3<=2,"fresher",AI3<=7,"early career",AI3<=15,"mid career",AI3<=25,"experienced",AI3>=26,"expert")} -> early career | AK3: 5 | AL3: {=_xlfn.IFS(AK3=0,"no training",AK3<=2,"low",AK3<=4,"moderate",AK3<=6,"high")} -> high | AM3: 3 | AN3: {=_xlfn.IFS(AM3=1,"low",AM3=2,"medium",AM3=3,"high",AM3=4,"very high")} -> high | AO3: 5 | AP3: {=_xlfn.IFS(AO3<=1,"new",AO3<=5,"early tenure",AO3<=10,"established",AO3<=20,"loyal",AO3>=21,"long term")} -> early tenure | AQ3: 4 | AR3: {=_xlfn.IFS(AQ3<=1,"new",AQ3<=4,"settling",AQ3<=7,"established",AQ3<=12,"stagnant risk",AQ3>12,"highly stagnant")} -> settling | AS3: 0 | AT3: {=_xlfn.IFS(AS3<=1,"recently promoted",AS3<=3,"due soon",AS3<=6,"over due",AS3>=7,"critically overdue")} -> recently promoted | AU3: 3 | AV3: {=_xlfn.IFS(AU3<=1,"new under manager",AU3<=4,"settling",AU3<=8,"established",AU3>=9,"long term")} -> settling
A4: 31 | B4: {=_xlfn.IFS(A4<=25,"early career",A4<=35,"mid career",A4<=45,"experienced",A4>=46,"senior")} -> mid career | C4: No | D4: Travel_Rarely | E4: Research & Development | F4: 26 | G4: {=_xlfn.IFS(F4<=5,"very near",F4<=10,"near",F4<=20,"moderate",F4<=29,"far")} -> far | H4: 1 | I4: {=_xlfn.IFS(H4=1,"Below College",H4= 2,"College",H4= 3,"Bachelor",H4= 4,"Master",H4= 5,"Doctor")} -> Below College | J4: Life Sciences | K4: 1 | L4: {=_xlfn.IFS(K4=1,"low",K4=2,"medium",K4=3,"high",K4=4,"very high")} -> low | M4: Male | N4: 3 | O4: {=_xlfn.IFS(N4=1,"low",N4=2,"medium",N4=3,"high",N4=4,"very high")} -> high | P4: 1 | Q4: {=_xlfn.IFS(P4=1,"junior",P4=2,"mid level",P4=3,"senior",P4=4,"lead",P4=5,"executive")} -> junior | R4: Research Scientist | S4: 3 | T4: {=_xlfn.IFS(S4=1,"low",S4=2,"medium",S4=3,"high",S4=4,"very high")} -> high | U4: Divorced | V4: 2911 | W4: 1 | X4: {=_xlfn.IFS(W4=0,"fresher",W4<=3,"stable",W4<=6,"moderate hopper",W4<=9,"frequent hopper")} -> stable | Y4: No | Z4: 17 | AA4: {=_xlfn.IFS(Z4<=14,"low hike",Z4<=18,"moderate hike",Z4<=22,"good hike",Z4<=25,"high hike")} -> moderate hike | AB4: 3 | AC4: {=_xlfn.IFS(AB4=1,"low",AB4=2,"good",AB4=3,"excellent",AB4=4,"outstanding")} -> excellent | AD4: 4 | AE4: {=_xlfn.IFS(AD4=1,"low",AD4=2,"medium",AD4=3,"high",AD4=4,"very high")} -> very high | AG4: 1 | AH4: {=_xlfn.IFS(AG4=0,"no stock options",AG4=2,"medium",AG4=3,"high",AG4=1,"low")} -> low | AI4: 5 | AJ4: {=_xlfn.IFS(AI4<=2,"fresher",AI4<=7,"early career",AI4<=15,"mid career",AI4<=25,"experienced",AI4>=26,"expert")} -> early career | AK4: 1 | AL4: {=_xlfn.IFS(AK4=0,"no training",AK4<=2,"low",AK4<=4,"moderate",AK4<=6,"high")} -> low | AM4: 2 | AN4: {=_xlfn.IFS(AM4=1,"low",AM4=2,"medium",AM4=3,"high",AM4=4,"very high")} -> medium | AO4: 5 | AP4: {=_xlfn.IFS(AO4<=1,"new",AO4<=5,"early tenure",AO4<=10,"established",AO4<=20,"loyal",AO4>=21,"long term")} -> early tenure | AQ4: 2 | AR4: {=_xlfn.IFS(AQ4<=1,"new",AQ4<=4,"settling",AQ4<=7,"established",AQ4<=12,"stagnant risk",AQ4>12,"highly stagnant")} -> settling | AS4: 4 | AT4: {=_xlfn.IFS(AS4<=1,"recently promoted",AS4<=3,"due soon",AS4<=6,"over due",AS4>=7,"critically overdue")} -> over due | AU4: 3 | AV4: {=_xlfn.IFS(AU4<=1,"new under manager",AU4<=4,"settling",AU4<=8,"established",AU4>=9,"long term")} -> settling
A5: 34 | B5: {=_xlfn.IFS(A5<=25,"early career",A5<=35,"mid career",A5<=45,"experienced",A5>=46,"senior")} -> mid career | C5: No | D5: Travel_Rarely | E5: Research & Development | F5: 19 | G5: {=_xlfn.IFS(F5<=5,"very near",F5<=10,"near",F5<=20,"moderate",F5<=29,"far")} -> moderate | H5: 2 | I5: {=_xlfn.IFS(H5=1,"Below College",H5= 2,"College",H5= 3,"Bachelor",H5= 4,"Master",H5= 5,"Doctor")} -> College | J5: Medical | K5: 2 | L5: {=_xlfn.IFS(K5=1,"low",K5=2,"medium",K5=3,"high",K5=4,"very high")} -> medium | M5: Male | N5: 3 | O5: {=_xlfn.IFS(N5=1,"low",N5=2,"medium",N5=3,"high",N5=4,"very high")} -> high | P5: 1 | Q5: {=_xlfn.IFS(P5=1,"junior",P5=2,"mid level",P5=3,"senior",P5=4,"lead",P5=5,"executive")} -> junior | R5: Laboratory Technician | S5: 4 | T5: {=_xlfn.IFS(S5=1,"low",S5=2,"medium",S5=3,"high",S5=4,"very high")} -> very high | U5: Divorced | V5: 2661 | W5: 0 | X5: {=_xlfn.IFS(W5=0,"fresher",W5<=3,"stable",W5<=6,"moderate hopper",W5<=9,"frequent hopper")} -> fresher | Y5: No | Z5: 11 | AA5: {=_xlfn.IFS(Z5<=14,"low hike",Z5<=18,"moderate hike",Z5<=22,"good hike",Z5<=25,"high hike")} -> low hike | AB5: 3 | AC5: {=_xlfn.IFS(AB5=1,"low",AB5=2,"good",AB5=3,"excellent",AB5=4,"outstanding")} -> excellent | AD5: 3 | AE5: {=_xlfn.IFS(AD5=1,"low",AD5=2,"medium",AD5=3,"high",AD5=4,"very high")} -> high | AG5: 1 | AH5: {=_xlfn.IFS(AG5=0,"no stock options",AG5=2,"medium",AG5=3,"high",AG5=1,"low")} -> low | AI5: 3 | AJ5: {=_xlfn.IFS(AI5<=2,"fresher",AI5<=7,"early career",AI5<=15,"mid career",AI5<=25,"experienced",AI5>=26,"expert")} -> early career | AK5: 2 | AL5: {=_xlfn.IFS(AK5=0,"no training",AK5<=2,"low",AK5<=4,"moderate",AK5<=6,"high")} -> low | AM5: 3 | AN5: {=_xlfn.IFS(AM5=1,"low",AM5=2,"medium",AM5=3,"high",AM5=4,"very high")} -> high | AO5: 2 | AP5: {=_xlfn.IFS(AO5<=1,"new",AO5<=5,"early tenure",AO5<=10,"established",AO5<=20,"loyal",AO5>=21,"long term")} -> early tenure | AQ5: 2 | AR5: {=_xlfn.IFS(AQ5<=1,"new",AQ5<=4,"settling",AQ5<=7,"established",AQ5<=12,"stagnant risk",AQ5>12,"highly stagnant")} -> settling | AS5: 1 | AT5: {=_xlfn.IFS(AS5<=1,"recently promoted",AS5<=3,"due soon",AS5<=6,"over due",AS5>=7,"critically overdue")} -> recently promoted | AU5: 2 | AV5: {=_xlfn.IFS(AU5<=1,"new under manager",AU5<=4,"settling",AU5<=8,"established",AU5>=9,"long term")} -> settling
A6: 28 | B6: {=_xlfn.IFS(A6<=25,"early career",A6<=35,"mid career",A6<=45,"experienced",A6>=46,"senior")} -> mid career | C6: Yes | D6: Travel_Rarely | E6: Research & Development | F6: 24 | G6: {=_xlfn.IFS(F6<=5,"very near",F6<=10,"near",F6<=20,"moderate",F6<=29,"far")} -> far | H6: 3 | I6: {=_xlfn.IFS(H6=1,"Below College",H6= 2,"College",H6= 3,"Bachelor",H6= 4,"Master",H6= 5,"Doctor")} -> Bachelor | J6: Life Sciences | K6: 3 | L6: {=_xlfn.IFS(K6=1,"low",K6=2,"medium",K6=3,"high",K6=4,"very high")} -> high | M6: Male | N6: 2 | O6: {=_xlfn.IFS(N6=1,"low",N6=2,"medium",N6=3,"high",N6=4,"very high")} -> medium | P6: 1 | Q6: {=_xlfn.IFS(P6=1,"junior",P6=2,"mid level",P6=3,"senior",P6=4,"lead",P6=5,"executive")} -> junior | R6: Laboratory Technician | S6: 3 | T6: {=_xlfn.IFS(S6=1,"low",S6=2,"medium",S6=3,"high",S6=4,"very high")} -> high | U6: Single | V6: 2028 | W6: 5 | X6: {=_xlfn.IFS(W6=0,"fresher",W6<=3,"stable",W6<=6,"moderate hopper",W6<=9,"frequent hopper")} -> moderate hopper | Y6: Yes | Z6: 14 | AA6: {=_xlfn.IFS(Z6<=14,"low hike",Z6<=18,"moderate hike",Z6<=22,"good hike",Z6<=25,"high hike")} -> low hike | AB6: 3 | AC6: {=_xlfn.IFS(AB6=1,"low",AB6=2,"good",AB6=3,"excellent",AB6=4,"outstanding")} -> excellent | AD6: 2 | AE6: {=_xlfn.IFS(AD6=1,"low",AD6=2,"medium",AD6=3,"high",AD6=4,"very high")} -> medium | AG6: 0 | AH6: {=_xlfn.IFS(AG6=0,"no stock options",AG6=2,"medium",AG6=3,"high",AG6=1,"low")} -> no stock options | AI6: 6 | AJ6: {=_xlfn.IFS(AI6<=2,"fresher",AI6<=7,"early career",AI6<=15,"mid career",AI6<=25,"experienced",AI6>=26,"expert")} -> early career | AK6: 4 | AL6: {=_xlfn.IFS(AK6=0,"no training",AK6<=2,"low",AK6<=4,"moderate",AK6<=6,"high")} -> moderate | AM6: 3 | AN6: {=_xlfn.IFS(AM6=1,"low",AM6=2,"medium",AM6=3,"high",AM6=4,"very high")} -> high | AO6: 4 | AP6: {=_xlfn.IFS(AO6<=1,"new",AO6<=5,"early tenure",AO6<=10,"established",AO6<=20,"loyal",AO6>=21,"long term")} -> early tenure | AQ6: 2 | AR6: {=_xlfn.IFS(AQ6<=1,"new",AQ6<=4,"settling",AQ6<=7,"established",AQ6<=12,"stagnant risk",AQ6>12,"highly stagnant")} -> settling | AS6: 0 | AT6: {=_xlfn.IFS(AS6<=1,"recently promoted",AS6<=3,"due soon",AS6<=6,"over due",AS6>=7,"critically overdue")} -> recently promoted | AU6: 3 | AV6: {=_xlfn.IFS(AU6<=1,"new under manager",AU6<=4,"settling",AU6<=8,"established",AU6>=9,"long term")} -> settling
A7: 38 | B7: {=_xlfn.IFS(A7<=25,"early career",A7<=35,"mid career",A7<=45,"experienced",A7>=46,"senior")} -> experienced | C7: No | D7: Travel_Rarely | E7: Research & Development | F7: 2 | G7: {=_xlfn.IFS(F7<=5,"very near",F7<=10,"near",F7<=20,"moderate",F7<=29,"far")} -> very near | H7: 3 | I7: {=_xlfn.IFS(H7=1,"Below College",H7= 2,"College",H7= 3,"Bachelor",H7= 4,"Master",H7= 5,"Doctor")} -> Bachelor | J7: Life Sciences | K7: 4 | L7: {=_xlfn.IFS(K7=1,"low",K7=2,"medium",K7=3,"high",K7=4,"very high")} -> very high | M7: Male | N7: 3 | O7: {=_xlfn.IFS(N7=1,"low",N7=2,"medium",N7=3,"high",N7=4,"very high")} -> high | P7: 1 | Q7: {=_xlfn.IFS(P7=1,"junior",P7=2,"mid level",P7=3,"senior",P7=4,"lead",P7=5,"executive")} -> junior | R7: Research Scientist | S7: 4 | T7: {=_xlfn.IFS(S7=1,"low",S7=2,"medium",S7=3,"high",S7=4,"very high")} -> very high | U7: Single | V7: 3944 | W7: 5 | X7: {=_xlfn.IFS(W7=0,"fresher",W7<=3,"stable",W7<=6,"moderate hopper",W7<=9,"frequent hopper")} -> moderate hopper | Y7: Yes | Z7: 11 | AA7: {=_xlfn.IFS(Z7<=14,"low hike",Z7<=18,"moderate hike",Z7<=22,"good hike",Z7<=25,"high hike")} -> low hike | AB7: 3 | AC7: {=_xlfn.IFS(AB7=1,"low",AB7=2,"good",AB7=3,"excellent",AB7=4,"outstanding")} -> excellent | AD7: 3 | AE7: {=_xlfn.IFS(AD7=1,"low",AD7=2,"medium",AD7=3,"high",AD7=4,"very high")} -> high | AG7: 0 | AH7: {=_xlfn.IFS(AG7=0,"no stock options",AG7=2,"medium",AG7=3,"high",AG7=1,"low")} -> no stock options | AI7: 6 | AJ7: {=_xlfn.IFS(AI7<=2,"fresher",AI7<=7,"early career",AI7<=15,"mid career",AI7<=25,"experienced",AI7>=26,"expert")} -> early career | AK7: 3 | AL7: {=_xlfn.IFS(AK7=0,"no training",AK7<=2,"low",AK7<=4,"moderate",AK7<=6,"high")} -> moderate | AM7: 3 | AN7: {=_xlfn.IFS(AM7=1,"low",AM7=2,"medium",AM7=3,"high",AM7=4,"very high")} -> high | AO7: 3 | AP7: {=_xlfn.IFS(AO7<=1,"new",AO7<=5,"early tenure",AO7<=10,"established",AO7<=20,"loyal",AO7>=21,"long term")} -> early tenure | AQ7: 2 | AR7: {=_xlfn.IFS(AQ7<=1,"new",AQ7<=4,"settling",AQ7<=7,"established",AQ7<=12,"stagnant risk",AQ7>12,"highly stagnant")} -> settling | AS7: 1 | AT7: {=_xlfn.IFS(AS7<=1,"recently promoted",AS7<=3,"due soon",AS7<=6,"over due",AS7>=7,"critically overdue")} -> recently promoted | AU7: 2 | AV7: {=_xlfn.IFS(AU7<=1,"new under manager",AU7<=4,"settling",AU7<=8,"established",AU7>=9,"long term")} -> settling
A8: 24 | B8: {=_xlfn.IFS(A8<=25,"early career",A8<=35,"mid career",A8<=45,"experienced",A8>=46,"senior")} -> early career | C8: No | D8: Non-Travel | E8: Research & Development | F8: 11 | G8: {=_xlfn.IFS(F8<=5,"very near",F8<=10,"near",F8<=20,"moderate",F8<=29,"far")} -> moderate | H8: 2 | I8: {=_xlfn.IFS(H8=1,"Below College",H8= 2,"College",H8= 3,"Bachelor",H8= 4,"Master",H8= 5,"Doctor")} -> College | J8: Other | K8: 1 | L8: {=_xlfn.IFS(K8=1,"low",K8=2,"medium",K8=3,"high",K8=4,"very high")} -> low | M8: Female | N8: 4 | O8: {=_xlfn.IFS(N8=1,"low",N8=2,"medium",N8=3,"high",N8=4,"very high")} -> very high | P8: 2 | Q8: {=_xlfn.IFS(P8=1,"junior",P8=2,"mid level",P8=3,"senior",P8=4,"lead",P8=5,"executive")} -> mid level | R8: Manufacturing Director | S8: 3 | T8: {=_xlfn.IFS(S8=1,"low",S8=2,"medium",S8=3,"high",S8=4,"very high")} -> high | U8: Divorced | V8: 4011 | W8: 0 | X8: {=_xlfn.IFS(W8=0,"fresher",W8<=3,"stable",W8<=6,"moderate hopper",W8<=9,"frequent hopper")} -> fresher | Y8: No | Z8: 18 | AA8: {=_xlfn.IFS(Z8<=14,"low hike",Z8<=18,"moderate hike",Z8<=22,"good hike",Z8<=25,"high hike")} -> moderate hike | AB8: 3 | AC8: {=_xlfn.IFS(AB8=1,"low",AB8=2,"good",AB8=3,"excellent",AB8=4,"outstanding")} -> excellent | AD8: 4 | AE8: {=_xlfn.IFS(AD8=1,"low",AD8=2,"medium",AD8=3,"high",AD8=4,"very high")} -> very high | AG8: 1 | AH8: {=_xlfn.IFS(AG8=0,"no stock options",AG8=2,"medium",AG8=3,"high",AG8=1,"low")} -> low | AI8: 5 | AJ8: {=_xlfn.IFS(AI8<=2,"fresher",AI8<=7,"early career",AI8<=15,"mid career",AI8<=25,"experienced",AI8>=26,"expert")} -> early career | AK8: 5 | AL8: {=_xlfn.IFS(AK8=0,"no training",AK8<=2,"low",AK8<=4,"moderate",AK8<=6,"high")} -> high | AM8: 2 | AN8: {=_xlfn.IFS(AM8=1,"low",AM8=2,"medium",AM8=3,"high",AM8=4,"very high")} -> medium | AO8: 4 | AP8: {=_xlfn.IFS(AO8<=1,"new",AO8<=5,"early tenure",AO8<=10,"established",AO8<=20,"loyal",AO8>=21,"long term")} -> early tenure | AQ8: 2 | AR8: {=_xlfn.IFS(AQ8<=1,"new",AQ8<=4,"settling",AQ8<=7,"established",AQ8<=12,"stagnant risk",AQ8>12,"highly stagnant")} -> settling | AS8: 1 | AT8: {=_xlfn.IFS(AS8<=1,"recently promoted",AS8<=3,"due soon",AS8<=6,"over due",AS8>=7,"critically overdue")} -> recently promoted | AU8: 3 | AV8: {=_xlfn.IFS(AU8<=1,"new under manager",AU8<=4,"settling",AU8<=8,"established",AU8>=9,"long term")} -> settling
A9: 36 | B9: {=_xlfn.IFS(A9<=25,"early career",A9<=35,"mid career",A9<=45,"experienced",A9>=46,"senior")} -> experienced | C9: Yes | D9: Travel_Rarely | E9: Sales | F9: 9 | G9: {=_xlfn.IFS(F9<=5,"very near",F9<=10,"near",F9<=20,"moderate",F9<=29,"far")} -> near | H9: 4 | I9: {=_xlfn.IFS(H9=1,"Below College",H9= 2,"College",H9= 3,"Bachelor",H9= 4,"Master",H9= 5,"Doctor")} -> Master | J9: Life Sciences | K9: 3 | L9: {=_xlfn.IFS(K9=1,"low",K9=2,"medium",K9=3,"high",K9=4,"very high")} -> high | M9: Male | N9: 2 | O9: {=_xlfn.IFS(N9=1,"low",N9=2,"medium",N9=3,"high",N9=4,"very high")} -> medium | P9: 1 | Q9: {=_xlfn.IFS(P9=1,"junior",P9=2,"mid level",P9=3,"senior",P9=4,"lead",P9=5,"executive")} -> junior | R9: Sales Representative | S9: 1 | T9: {=_xlfn.IFS(S9=1,"low",S9=2,"medium",S9=3,"high",S9=4,"very high")} -> low | U9: Single | V9: 3407 | W9: 7 | X9: {=_xlfn.IFS(W9=0,"fresher",W9<=3,"stable",W9<=6,"moderate hopper",W9<=9,"frequent hopper")} -> frequent hopper | Y9: No | Z9: 23 | AA9: {=_xlfn.IFS(Z9<=14,"low hike",Z9<=18,"moderate hike",Z9<=22,"good hike",Z9<=25,"high hike")} -> high hike | AB9: 4 | AC9: {=_xlfn.IFS(AB9=1,"low",AB9=2,"good",AB9=3,"excellent",AB9=4,"outstanding")} -> outstanding | AD9: 2 | AE9: {=_xlfn.IFS(AD9=1,"low",AD9=2,"medium",AD9=3,"high",AD9=4,"very high")} -> medium | AG9: 0 | AH9: {=_xlfn.IFS(AG9=0,"no stock options",AG9=2,"medium",AG9=3,"high",AG9=1,"low")} -> no stock options | AI9: 10 | AJ9: {=_xlfn.IFS(AI9<=2,"fresher",AI9<=7,"early career",AI9<=15,"mid career",AI9<=25,"experienced",AI9>=26,"expert")} -> mid career | AK9: 4 | AL9: {=_xlfn.IFS(AK9=0,"no training",AK9<=2,"low",AK9<=4,"moderate",AK9<=6,"high")} -> moderate | AM9: 3 | AN9: {=_xlfn.IFS(AM9=1,"low",AM9=2,"medium",AM9=3,"high",AM9=4,"very high")} -> high | AO9: 5 | AP9: {=_xlfn.IFS(AO9<=1,"new",AO9<=5,"early tenure",AO9<=10,"established",AO9<=20,"loyal",AO9>=21,"long term")} -> early tenure | AQ9: 3 | AR9: {=_xlfn.IFS(AQ9<=1,"new",AQ9<=4,"settling",AQ9<=7,"established",AQ9<=12,"stagnant risk",AQ9>12,"highly stagnant")} -> settling | AS9: 0 | AT9: {=_xlfn.IFS(AS9<=1,"recently promoted",AS9<=3,"due soon",AS9<=6,"over due",AS9>=7,"critically overdue")} -> recently promoted | AU9: 3 | AV9: {=_xlfn.IFS(AU9<=1,"new under manager",AU9<=4,"settling",AU9<=8,"established",AU9>=9,"long term")} -> settling
A10: 34 | B10: {=_xlfn.IFS(A10<=25,"early career",A10<=35,"mid career",A10<=45,"experienced",A10>=46,"senior")} -> mid career | C10: Yes | D10: Travel_Rarely | E10: Research & Development | F10: 6 | G10: {=_xlfn.IFS(F10<=5,"very near",F10<=10,"near",F10<=20,"moderate",F10<=29,"far")} -> near | H10: 1 | I10: {=_xlfn.IFS(H10=1,"Below College",H10= 2,"College",H10= 3,"Bachelor",H10= 4,"Master",H10= 5,"Doctor")} -> Below College | J10: Medical | K10: 2 | L10: {=_xlfn.IFS(K10=1,"low",K10=2,"medium",K10=3,"high",K10=4,"very high")} -> medium | M10: Male | N10: 3 | O10: {=_xlfn.IFS(N10=1,"low",N10=2,"medium",N10=3,"high",N10=4,"very high")} -> high | P10: 1 | Q10: {=_xlfn.IFS(P10=1,"junior",P10=2,"mid level",P10=3,"senior",P10=4,"lead",P10=5,"executive")} -> junior | R10: Research Scientist | S10: 1 | T10: {=_xlfn.IFS(S10=1,"low",S10=2,"medium",S10=3,"high",S10=4,"very high")} -> low | U10: Single | V10: 2960 | W10: 2 | X10: {=_xlfn.IFS(W10=0,"fresher",W10<=3,"stable",W10<=6,"moderate hopper",W10<=9,"frequent hopper")} -> stable | Y10: No | Z10: 11 | AA10: {=_xlfn.IFS(Z10<=14,"low hike",Z10<=18,"moderate hike",Z10<=22,"good hike",Z10<=25,"high hike")} -> low hike | AB10: 3 | AC10: {=_xlfn.IFS(AB10=1,"low",AB10=2,"good",AB10=3,"excellent",AB10=4,"outstanding")} -> excellent | AD10: 3 | AE10: {=_xlfn.IFS(AD10=1,"low",AD10=2,"medium",AD10=3,"high",AD10=4,"very high")} -> high | AG10: 0 | AH10: {=_xlfn.IFS(AG10=0,"no stock options",AG10=2,"medium",AG10=3,"high",AG10=1,"low")} -> no stock options | AI10: 8 | AJ10: {=_xlfn.IFS(AI10<=2,"fresher",AI10<=7,"early career",AI10<=15,"mid career",AI10<=25,"experienced",AI10>=26,"expert")} -> mid career | AK10: 2 | AL10: {=_xlfn.IFS(AK10=0,"no training",AK10<=2,"low",AK10<=4,"moderate",AK10<=6,"high")} -> low | AM10: 3 | AN10: {=_xlfn.IFS(AM10=1,"low",AM10=2,"medium",AM10=3,"high",AM10=4,"very high")} -> high | AO10: 4 | AP10: {=_xlfn.IFS(AO10<=1,"new",AO10<=5,"early tenure",AO10<=10,"established",AO10<=20,"loyal",AO10>=21,"long term")} -> early tenure | AQ10: 2 | AR10: {=_xlfn.IFS(AQ10<=1,"new",AQ10<=4,"settling",AQ10<=7,"established",AQ10<=12,"stagnant risk",AQ10>12,"highly stagnant")} -> settling | AS10: 1 | AT10: {=_xlfn.IFS(AS10<=1,"recently promoted",AS10<=3,"due soon",AS10<=6,"over due",AS10>=7,"critically overdue")} -> recently promoted | AU10: 3 | AV10: {=_xlfn.IFS(AU10<=1,"new under manager",AU10<=4,"settling",AU10<=8,"established",AU10>=9,"long term")} -> settling
A11: 46 | B11: {=_xlfn.IFS(A11<=25,"early career",A11<=35,"mid career",A11<=45,"experienced",A11>=46,"senior")} -> senior | C11: No | D11: Travel_Rarely | E11: Sales | F11: 2 | G11: {=_xlfn.IFS(F11<=5,"very near",F11<=10,"near",F11<=20,"moderate",F11<=29,"far")} -> very near | H11: 4 | I11: {=_xlfn.IFS(H11=1,"Below College",H11= 2,"College",H11= 3,"Bachelor",H11= 4,"Master",H11= 5,"Doctor")} -> Master | J11: Marketing | K11: 2 | L11: {=_xlfn.IFS(K11=1,"low",K11=2,"medium",K11=3,"high",K11=4,"very high")} -> medium | M11: Female | N11: 3 | O11: {=_xlfn.IFS(N11=1,"low",N11=2,"medium",N11=3,"high",N11=4,"very high")} -> high | P11: 5 | Q11: {=_xlfn.IFS(P11=1,"junior",P11=2,"mid level",P11=3,"senior",P11=4,"lead",P11=5,"executive")} -> executive | R11: Manager | S11: 1 | T11: {=_xlfn.IFS(S11=1,"low",S11=2,"medium",S11=3,"high",S11=4,"very high")} -> low | U11: Single | V11: 18947 | W11: 3 | X11: {=_xlfn.IFS(W11=0,"fresher",W11<=3,"stable",W11<=6,"moderate hopper",W11<=9,"frequent hopper")} -> stable | Y11: No | Z11: 12 | AA11: {=_xlfn.IFS(Z11<=14,"low hike",Z11<=18,"moderate hike",Z11<=22,"good hike",Z11<=25,"high hike")} -> low hike | AB11: 3 | AC11: {=_xlfn.IFS(AB11=1,"low",AB11=2,"good",AB11=3,"excellent",AB11=4,"outstanding")} -> excellent | AD11: 4 | AE11: {=_xlfn.IFS(AD11=1,"low",AD11=2,"medium",AD11=3,"high",AD11=4,"very high")} -> very high | AG11: 0 | AH11: {=_xlfn.IFS(AG11=0,"no stock options",AG11=2,"medium",AG11=3,"high",AG11=1,"low")} -> no stock options | AI11: 22 | AJ11: {=_xlfn.IFS(AI11<=2,"fresher",AI11<=7,"early career",AI11<=15,"mid career",AI11<=25,"experienced",AI11>=26,"expert")} -> experienced | AK11: 2 | AL11: {=_xlfn.IFS(AK11=0,"no training",AK11<=2,"low",AK11<=4,"moderate",AK11<=6,"high")} -> low | AM11: 2 | AN11: {=_xlfn.IFS(AM11=1,"low",AM11=2,"medium",AM11=3,"high",AM11=4,"very high")} -> medium | AO11: 2 | AP11: {=_xlfn.IFS(AO11<=1,"new",AO11<=5,"early tenure",AO11<=10,"established",AO11<=20,"loyal",AO11>=21,"long term")} -> early tenure | AQ11: 2 | AR11: {=_xlfn.IFS(AQ11<=1,"new",AQ11<=4,"settling",AQ11<=7,"established",AQ11<=12,"stagnant risk",AQ11>12,"highly stagnant")} -> settling | AS11: 2 | AT11: {=_xlfn.IFS(AS11<=1,"recently promoted",AS11<=3,"due soon",AS11<=6,"over due",AS11>=7,"critically overdue")} -> due soon | AU11: 1 | AV11: {=_xlfn.IFS(AU11<=1,"new under manager",AU11<=4,"settling",AU11<=8,"established",AU11>=9,"long term")} -> new under manager
A12: 44 | B12: {=_xlfn.IFS(A12<=25,"early career",A12<=35,"mid career",A12<=45,"experienced",A12>=46,"senior")} -> experienced | C12: No | D12: Travel_Rarely | E12: Research & Development | F12: 10 | G12: {=_xlfn.IFS(F12<=5,"very near",F12<=10,"near",F12<=20,"moderate",F12<=29,"far")} -> near | H12: 4 | I12: {=_xlfn.IFS(H12=1,"Below College",H12= 2,"College",H12= 3,"Bachelor",H12= 4,"Master",H12= 5,"Doctor")} -> Master | J12: Other | K12: 4 | L12: {=_xlfn.IFS(K12=1,"low",K12=2,"medium",K12=3,"high",K12=4,"very high")} -> very high | M12: Male | N12: 3 | O12: {=_xlfn.IFS(N12=1,"low",N12=2,"medium",N12=3,"high",N12=4,"very high")} -> high | P12: 2 | Q12: {=_xlfn.IFS(P12=1,"junior",P12=2,"mid level",P12=3,"senior",P12=4,"lead",P12=5,"executive")} -> mid level | R12: Healthcare Representative | S12: 4 | T12: {=_xlfn.IFS(S12=1,"low",S12=2,"medium",S12=3,"high",S12=4,"very high")} -> very high | U12: Married | V12: 6465 | W12: 2 | X12: {=_xlfn.IFS(W12=0,"fresher",W12<=3,"stable",W12<=6,"moderate hopper",W12<=9,"frequent hopper")} -> stable | Y12: Yes | Z12: 13 | AA12: {=_xlfn.IFS(Z12<=14,"low hike",Z12<=18,"moderate hike",Z12<=22,"good hike",Z12<=25,"high hike")} -> low hike | AB12: 3 | AC12: {=_xlfn.IFS(AB12=1,"low",AB12=2,"good",AB12=3,"excellent",AB12=4,"outstanding")} -> excellent | AD12: 4 | AE12: {=_xlfn.IFS(AD12=1,"low",AD12=2,"medium",AD12=3,"high",AD12=4,"very high")} -> very high | AG12: 0 | AH12: {=_xlfn.IFS(AG12=0,"no stock options",AG12=2,"medium",AG12=3,"high",AG12=1,"low")} -> no stock options | AI12: 9 | AJ12: {=_xlfn.IFS(AI12<=2,"fresher",AI12<=7,"early career",AI12<=15,"mid career",AI12<=25,"experienced",AI12>=26,"expert")} -> mid career | AK12: 5 | AL12: {=_xlfn.IFS(AK12=0,"no training",AK12<=2,"low",AK12<=4,"moderate",AK12<=6,"high")} -> high | AM12: 4 | AN12: {=_xlfn.IFS(AM12=1,"low",AM12=2,"medium",AM12=3,"high",AM12=4,"very high")} -> very high | AO12: 4 | AP12: {=_xlfn.IFS(AO12<=1,"new",AO12<=5,"early tenure",AO12<=10,"established",AO12<=20,"loyal",AO12>=21,"long term")} -> early tenure | AQ12: 2 | AR12: {=_xlfn.IFS(AQ12<=1,"new",AQ12<=4,"settling",AQ12<=7,"established",AQ12<=12,"stagnant risk",AQ12>12,"highly stagnant")} -> settling | AS12: 1 | AT12: {=_xlfn.IFS(AS12<=1,"recently promoted",AS12<=3,"due soon",AS12<=6,"over due",AS12>=7,"critically overdue")} -> recently promoted | AU12: 3 | AV12: {=_xlfn.IFS(AU12<=1,"new under manager",AU12<=4,"settling",AU12<=8,"established",AU12>=9,"long term")} -> settling
A13: 24 | B13: {=_xlfn.IFS(A13<=25,"early career",A13<=35,"mid career",A13<=45,"experienced",A13>=46,"senior")} -> early career | C13: Yes | D13: Travel_Rarely | E13: Research & Development | F13: 1 | G13: {=_xlfn.IFS(F13<=5,"very near",F13<=10,"near",F13<=20,"moderate",F13<=29,"far")} -> very near | H13: 3 | I13: {=_xlfn.IFS(H13=1,"Below College",H13= 2,"College",H13= 3,"Bachelor",H13= 4,"Master",H13= 5,"Doctor")} -> Bachelor | J13: Medical | K13: 2 | L13: {=_xlfn.IFS(K13=1,"low",K13=2,"medium",K13=3,"high",K13=4,"very high")} -> medium | M13: Male | N13: 3 | O13: {=_xlfn.IFS(N13=1,"low",N13=2,"medium",N13=3,"high",N13=4,"very high")} -> high | P13: 1 | Q13: {=_xlfn.IFS(P13=1,"junior",P13=2,"mid level",P13=3,"senior",P13=4,"lead",P13=5,"executive")} -> junior | R13: Research Scientist | S13: 4 | T13: {=_xlfn.IFS(S13=1,"low",S13=2,"medium",S13=3,"high",S13=4,"very high")} -> very high | U13: Married | V13: 2293 | W13: 2 | X13: {=_xlfn.IFS(W13=0,"fresher",W13<=3,"stable",W13<=6,"moderate hopper",W13<=9,"frequent hopper")} -> stable | Y13: Yes | Z13: 16 | AA13: {=_xlfn.IFS(Z13<=14,"low hike",Z13<=18,"moderate hike",Z13<=22,"good hike",Z13<=25,"high hike")} -> moderate hike | AB13: 3 | AC13: {=_xlfn.IFS(AB13=1,"low",AB13=2,"good",AB13=3,"excellent",AB13=4,"outstanding")} -> excellent | AD13: 1 | AE13: {=_xlfn.IFS(AD13=1,"low",AD13=2,"medium",AD13=3,"high",AD13=4,"very high")} -> low | AG13: 1 | AH13: {=_xlfn.IFS(AG13=0,"no stock options",AG13=2,"medium",AG13=3,"high",AG13=1,"low")} -> low | AI13: 6 | AJ13: {=_xlfn.IFS(AI13<=2,"fresher",AI13<=7,"early career",AI13<=15,"mid career",AI13<=25,"experienced",AI13>=26,"expert")} -> early career | AK13: 2 | AL13: {=_xlfn.IFS(AK13=0,"no training",AK13<=2,"low",AK13<=4,"moderate",AK13<=6,"high")} -> low | AM13: 2 | AN13: {=_xlfn.IFS(AM13=1,"low",AM13=2,"medium",AM13=3,"high",AM13=4,"very high")} -> medium | AO13: 2 | AP13: {=_xlfn.IFS(AO13<=1,"new",AO13<=5,"early tenure",AO13<=10,"established",AO13<=20,"loyal",AO13>=21,"long term")} -> early tenure | AQ13: 0 | AR13: {=_xlfn.IFS(AQ13<=1,"new",AQ13<=4,"settling",AQ13<=7,"established",AQ13<=12,"stagnant risk",AQ13>12,"highly stagnant")} -> new | AS13: 2 | AT13: {=_xlfn.IFS(AS13<=1,"recently promoted",AS13<=3,"due soon",AS13<=6,"over due",AS13>=7,"critically overdue")} -> due soon | AU13: 0 | AV13: {=_xlfn.IFS(AU13<=1,"new under manager",AU13<=4,"settling",AU13<=8,"established",AU13>=9,"long term")} -> new under manager
... A562: 34 | B562: {=_xlfn.IFS(A562<=25,"early career",A562<=35,"mid career",A562<=45,"experienced",A562>=46,"senior")} -> mid career | C562: No | D562: Travel_Rarely | E562: Research & Development | F562: 8 | G562: {=_xlfn.IFS(F562<=5,"very near",F562<=10,"near",F562<=20,"moderate",F562<=29,"far")} -> near | H562: 3 | I562: {=_xlfn.IFS(H562=1,"Below College",H562= 2,"College",H562= 3,"Bachelor",H562= 4,"Master",H562= 5,"Doctor")} -> Bachelor | J562: Medical | K562: 2 | L562: {=_xlfn.IFS(K562=1,"low",K562=2,"medium",K562=3,"high",K562=4,"very high")} -> medium | M562: Male | N562: 4 | O562: {=_xlfn.IFS(N562=1,"low",N562=2,"medium",N562=3,"high",N562=4,"very high")} -> very high | P562: 2 | Q562: {=_xlfn.IFS(P562=1,"junior",P562=2,"mid level",P562=3,"senior",P562=4,"lead",P562=5,"executive")} -> mid level | R562: Laboratory Technician | S562: 3 | T562: {=_xlfn.IFS(S562=1,"low",S562=2,"medium",S562=3,"high",S562=4,"very high")} -> high | U562: Married | V562: 4404 | W562: 2 | X562: {=_xlfn.IFS(W562=0,"fresher",W562<=3,"stable",W562<=6,"moderate hopper",W562<=9,"frequent hopper")} -> stable | Y562: No | Z562: 12 | AA562: {=_xlfn.IFS(Z562<=14,"low hike",Z562<=18,"moderate hike",Z562<=22,"good hike",Z562<=25,"high hike")} -> low hike | AB562: 3 | AC562: {=_xlfn.IFS(AB562=1,"low",AB562=2,"good",AB562=3,"excellent",AB562=4,"outstanding")} -> excellent | AD562: 1 | AE562: {=_xlfn.IFS(AD562=1,"low",AD562=2,"medium",AD562=3,"high",AD562=4,"very high")} -> low | AG562: 0 | AH562: {=_xlfn.IFS(AG562=0,"no stock options",AG562=2,"medium",AG562=3,"high",AG562=1,"low")} -> no stock options | AI562: 6 | AJ562: {=_xlfn.IFS(AI562<=2,"fresher",AI562<=7,"early career",AI562<=15,"mid career",AI562<=25,"experienced",AI562>=26,"expert")} -> early career | AK562: 3 | AL562: {=_xlfn.IFS(AK562=0,"no training",AK562<=2,"low",AK562<=4,"moderate",AK562<=6,"high")} -> moderate | AM562: 4 | AN562: {=_xlfn.IFS(AM562=1,"low",AM562=2,"medium",AM562=3,"high",AM562=4,"very high")} -> very high | AO562: 4 | AP562: {=_xlfn.IFS(AO562<=1,"new",AO562<=5,"early tenure",AO562<=10,"established",AO562<=20,"loyal",AO562>=21,"long term")} -> early tenure | AQ562: 3 | AR562: {=_xlfn.IFS(AQ562<=1,"new",AQ562<=4,"settling",AQ562<=7,"established",AQ562<=12,"stagnant risk",AQ562>12,"highly stagnant")} -> settling | AS562: 1 | AT562: {=_xlfn.IFS(AS562<=1,"recently promoted",AS562<=3,"due soon",AS562<=6,"over due",AS562>=7,"critically overdue")} -> recently promoted | AU562: 2 | AV562: {=_xlfn.IFS(AU562<=1,"new under manager",AU562<=4,"settling",AU562<=8,"established",AU562>=9,"long term")} -> settling
A563: 41 | B563: {=_xlfn.IFS(A563<=25,"early career",A563<=35,"mid career",A563<=45,"experienced",A563>=46,"senior")} -> experienced | C563: Yes | D563: Travel_Rarely | E563: Sales | F563: 1 | G563: {=_xlfn.IFS(F563<=5,"very near",F563<=10,"near",F563<=20,"moderate",F563<=29,"far")} -> very near | H563: 2 | I563: {=_xlfn.IFS(H563=1,"Below College",H563= 2,"College",H563= 3,"Bachelor",H563= 4,"Master",H563= 5,"Doctor")} -> College | J563: Life Sciences | K563: 2 | L563: {=_xlfn.IFS(K563=1,"low",K563=2,"medium",K563=3,"high",K563=4,"very high")} -> medium | M563: Female | N563: 3 | O563: {=_xlfn.IFS(N563=1,"low",N563=2,"medium",N563=3,"high",N563=4,"very high")} -> high | P563: 2 | Q563: {=_xlfn.IFS(P563=1,"junior",P563=2,"mid level",P563=3,"senior",P563=4,"lead",P563=5,"executive")} -> mid level | R563: Sales Executive | S563: 4 | T563: {=_xlfn.IFS(S563=1,"low",S563=2,"medium",S563=3,"high",S563=4,"very high")} -> very high | U563: Single | V563: 5993 | W563: 8 | X563: {=_xlfn.IFS(W563=0,"fresher",W563<=3,"stable",W563<=6,"moderate hopper",W563<=9,"frequent hopper")} -> frequent hopper | Y563: Yes | Z563: 11 | AA563: {=_xlfn.IFS(Z563<=14,"low hike",Z563<=18,"moderate hike",Z563<=22,"good hike",Z563<=25,"high hike")} -> low hike | AB563: 3 | AC563: {=_xlfn.IFS(AB563=1,"low",AB563=2,"good",AB563=3,"excellent",AB563=4,"outstanding")} -> excellent | AD563: 1 | AE563: {=_xlfn.IFS(AD563=1,"low",AD563=2,"medium",AD563=3,"high",AD563=4,"very high")} -> low | AF563: {=_xlfn.IFS(AD563=1,"low",AD563=2,"medium",AD563=3,"high",AD563=4,"very high")} -> low | AG563: 0 | AH563: {=_xlfn.IFS(AG563=0,"no stock options",AG563=2,"medium",AG563=3,"high",AG563=1,"low")} -> no stock options | AI563: 8 | AJ563: {=_xlfn.IFS(AI563<=2,"fresher",AI563<=7,"early career",AI563<=15,"mid career",AI563<=25,"experienced",AI563>=26,"expert")} -> mid career | AK563: 0 | AL563: {=_xlfn.IFS(AK563=0,"no training",AK563<=2,"low",AK563<=4,"moderate",AK563<=6,"high")} -> no training | AM563: 1 | AN563: {=_xlfn.IFS(AM563=1,"low",AM563=2,"medium",AM563=3,"high",AM563=4,"very high")} -> low | AO563: 6 | AP563: {=_xlfn.IFS(AO563<=1,"new",AO563<=5,"early tenure",AO563<=10,"established",AO563<=20,"loyal",AO563>=21,"long term")} -> established | AQ563: 4 | AR563: {=_xlfn.IFS(AQ563<=1,"new",AQ563<=4,"settling",AQ563<=7,"established",AQ563<=12,"stagnant risk",AQ563>12,"highly stagnant")} -> settling | AS563: 0 | AT563: {=_xlfn.IFS(AS563<=1,"recently promoted",AS563<=3,"due soon",AS563<=6,"over due",AS563>=7,"critically overdue")} -> recently promoted | AU563: 5 | AV563: {=_xlfn.IFS(AU563<=1,"new under manager",AU563<=4,"settling",AU563<=8,"established",AU563>=9,"long term")} -> established
A564: 49 | B564: {=_xlfn.IFS(A564<=25,"early career",A564<=35,"mid career",A564<=45,"experienced",A564>=46,"senior")} -> senior | C564: No | D564: Travel_Frequently | E564: Research & Development | F564: 8 | G564: {=_xlfn.IFS(F564<=5,"very near",F564<=10,"near",F564<=20,"moderate",F564<=29,"far")} -> near | H564: 1 | I564: {=_xlfn.IFS(H564=1,"Below College",H564= 2,"College",H564= 3,"Bachelor",H564= 4,"Master",H564= 5,"Doctor")} -> Below College | J564: Life Sciences | K564: 3 | L564: {=_xlfn.IFS(K564=1,"low",K564=2,"medium",K564=3,"high",K564=4,"very high")} -> high | M564: Male | N564: 2 | O564: {=_xlfn.IFS(N564=1,"low",N564=2,"medium",N564=3,"high",N564=4,"very high")} -> medium | P564: 2 | Q564: {=_xlfn.IFS(P564=1,"junior",P564=2,"mid level",P564=3,"senior",P564=4,"lead",P564=5,"executive")} -> mid level | R564: Research Scientist | S564: 2 | T564: {=_xlfn.IFS(S564=1,"low",S564=2,"medium",S564=3,"high",S564=4,"very high")} -> medium | U564: Married | V564: 5130 | W564: 1 | X564: {=_xlfn.IFS(W564=0,"fresher",W564<=3,"stable",W564<=6,"moderate hopper",W564<=9,"frequent hopper")} -> stable | Y564: No | Z564: 23 | AA564: {=_xlfn.IFS(Z564<=14,"low hike",Z564<=18,"moderate hike",Z564<=22,"good hike",Z564<=25,"high hike")} -> high hike | AB564: 4 | AC564: {=_xlfn.IFS(AB564=1,"low",AB564=2,"good",AB564=3,"excellent",AB564=4,"outstanding")} -> outstanding | AD564: 4 | AE564: {=_xlfn.IFS(AD564=1,"low",AD564=2,"medium",AD564=3,"high",AD564=4,"very high")} -> very high | AG564: 1 | AH564: {=_xlfn.IFS(AG564=0,"no stock options",AG564=2,"medium",AG564=3,"high",AG564=1,"low")} -> low | AI564: 10 | AJ564: {=_xlfn.IFS(AI564<=2,"fresher",AI564<=7,"early career",AI564<=15,"mid career",AI564<=25,"experienced",AI564>=26,"expert")} -> mid career | AK564: 3 | AL564: {=_xlfn.IFS(AK564=0,"no training",AK564<=2,"low",AK564<=4,"moderate",AK564<=6,"high")} -> moderate | AM564: 3 | AN564: {=_xlfn.IFS(AM564=1,"low",AM564=2,"medium",AM564=3,"high",AM564=4,"very high")} -> high | AO564: 10 | AP564: {=_xlfn.IFS(AO564<=1,"new",AO564<=5,"early tenure",AO564<=10,"established",AO564<=20,"loyal",AO564>=21,"long term")} -> established | AQ564: 7 | AR564: {=_xlfn.IFS(AQ564<=1,"new",AQ564<=4,"settling",AQ564<=7,"established",AQ564<=12,"stagnant risk",AQ564>12,"highly stagnant")} -> established | AS564: 1 | AT564: {=_xlfn.IFS(AS564<=1,"recently promoted",AS564<=3,"due soon",AS564<=6,"over due",AS564>=7,"critically overdue")} -> recently promoted | AU564: 7 | AV564: {=_xlfn.IFS(AU564<=1,"new under manager",AU564<=4,"settling",AU564<=8,"established",AU564>=9,"long term")} -> established
A565: 33 | B565: {=_xlfn.IFS(A565<=25,"early career",A565<=35,"mid career",A565<=45,"experienced",A565>=46,"senior")} -> mid career | C565: No | D565: Travel_Frequently | E565: Research & Development | F565: 3 | G565: {=_xlfn.IFS(F565<=5,"very near",F565<=10,"near",F565<=20,"moderate",F565<=29,"far")} -> very near | H565: 4 | I565: {=_xlfn.IFS(H565=1,"Below College",H565= 2,"College",H565= 3,"Bachelor",H565= 4,"Master",H565= 5,"Doctor")} -> Master | J565: Life Sciences | K565: 4 | L565: {=_xlfn.IFS(K565=1,"low",K565=2,"medium",K565=3,"high",K565=4,"very high")} -> very high | M565: Female | N565: 3 | O565: {=_xlfn.IFS(N565=1,"low",N565=2,"medium",N565=3,"high",N565=4,"very high")} -> high | P565: 1 | Q565: {=_xlfn.IFS(P565=1,"junior",P565=2,"mid level",P565=3,"senior",P565=4,"lead",P565=5,"executive")} -> junior | R565: Research Scientist | S565: 3 | T565: {=_xlfn.IFS(S565=1,"low",S565=2,"medium",S565=3,"high",S565=4,"very high")} -> high | U565: Married | V565: 2909 | W565: 1 | X565: {=_xlfn.IFS(W565=0,"fresher",W565<=3,"stable",W565<=6,"moderate hopper",W565<=9,"frequent hopper")} -> stable | Y565: Yes | Z565: 11 | AA565: {=_xlfn.IFS(Z565<=14,"low hike",Z565<=18,"moderate hike",Z565<=22,"good hike",Z565<=25,"high hike")} -> low hike | AB565: 3 | AC565: {=_xlfn.IFS(AB565=1,"low",AB565=2,"good",AB565=3,"excellent",AB565=4,"outstanding")} -> excellent | AD565: 3 | AE565: {=_xlfn.IFS(AD565=1,"low",AD565=2,"medium",AD565=3,"high",AD565=4,"very high")} -> high | AG565: 0 | AH565: {=_xlfn.IFS(AG565=0,"no stock options",AG565=2,"medium",AG565=3,"high",AG565=1,"low")} -> no stock options | AI565: 8 | AJ565: {=_xlfn.IFS(AI565<=2,"fresher",AI565<=7,"early career",AI565<=15,"mid career",AI565<=25,"experienced",AI565>=26,"expert")} -> mid career | AK565: 3 | AL565: {=_xlfn.IFS(AK565=0,"no training",AK565<=2,"low",AK565<=4,"moderate",AK565<=6,"high")} -> moderate | AM565: 3 | AN565: {=_xlfn.IFS(AM565=1,"low",AM565=2,"medium",AM565=3,"high",AM565=4,"very high")} -> high | AO565: 8 | AP565: {=_xlfn.IFS(AO565<=1,"new",AO565<=5,"early tenure",AO565<=10,"established",AO565<=20,"loyal",AO565>=21,"long term")} -> established | AQ565: 7 | AR565: {=_xlfn.IFS(AQ565<=1,"new",AQ565<=4,"settling",AQ565<=7,"established",AQ565<=12,"stagnant risk",AQ565>12,"highly stagnant")} -> established | AS565: 3 | AT565: {=_xlfn.IFS(AS565<=1,"recently promoted",AS565<=3,"due soon",AS565<=6,"over due",AS565>=7,"critically overdue")} -> due soon | AU565: 0 | AV565: {=_xlfn.IFS(AU565<=1,"new under manager",AU565<=4,"settling",AU565<=8,"established",AU565>=9,"long term")} -> new under manager
A566: 32 | B566: {=_xlfn.IFS(A566<=25,"early career",A566<=35,"mid career",A566<=45,"experienced",A566>=46,"senior")} -> mid career | C566: No | D566: Travel_Frequently | E566: Research & Development | F566: 2 | G566: {=_xlfn.IFS(F566<=5,"very near",F566<=10,"near",F566<=20,"moderate",F566<=29,"far")} -> very near | H566: 2 | I566: {=_xlfn.IFS(H566=1,"Below College",H566= 2,"College",H566= 3,"Bachelor",H566= 4,"Master",H566= 5,"Doctor")} -> College | J566: Life Sciences | K566: 4 | L566: {=_xlfn.IFS(K566=1,"low",K566=2,"medium",K566=3,"high",K566=4,"very high")} -> very high | M566: Male | N566: 3 | O566: {=_xlfn.IFS(N566=1,"low",N566=2,"medium",N566=3,"high",N566=4,"very high")} -> high | P566: 1 | Q566: {=_xlfn.IFS(P566=1,"junior",P566=2,"mid level",P566=3,"senior",P566=4,"lead",P566=5,"executive")} -> junior | R566: Laboratory Technician | S566: 4 | T566: {=_xlfn.IFS(S566=1,"low",S566=2,"medium",S566=3,"high",S566=4,"very high")} -> very high | U566: Single | V566: 3068 | W566: 0 | X566: {=_xlfn.IFS(W566=0,"fresher",W566<=3,"stable",W566<=6,"moderate hopper",W566<=9,"frequent hopper")} -> fresher | Y566: No | Z566: 13 | AA566: {=_xlfn.IFS(Z566<=14,"low hike",Z566<=18,"moderate hike",Z566<=22,"good hike",Z566<=25,"high hike")} -> low hike | AB566: 3 | AC566: {=_xlfn.IFS(AB566=1,"low",AB566=2,"good",AB566=3,"excellent",AB566=4,"outstanding")} -> excellent | AD566: 3 | AE566: {=_xlfn.IFS(AD566=1,"low",AD566=2,"medium",AD566=3,"high",AD566=4,"very high")} -> high | AG566: 0 | AH566: {=_xlfn.IFS(AG566=0,"no stock options",AG566=2,"medium",AG566=3,"high",AG566=1,"low")} -> no stock options | AI566: 8 | AJ566: {=_xlfn.IFS(AI566<=2,"fresher",AI566<=7,"early career",AI566<=15,"mid career",AI566<=25,"experienced",AI566>=26,"expert")} -> mid career | AK566: 2 | AL566: {=_xlfn.IFS(AK566=0,"no training",AK566<=2,"low",AK566<=4,"moderate",AK566<=6,"high")} -> low | AM566: 2 | AN566: {=_xlfn.IFS(AM566=1,"low",AM566=2,"medium",AM566=3,"high",AM566=4,"very high")} -> medium | AO566: 7 | AP566: {=_xlfn.IFS(AO566<=1,"new",AO566<=5,"early tenure",AO566<=10,"established",AO566<=20,"loyal",AO566>=21,"long term")} -> established | AQ566: 7 | AR566: {=_xlfn.IFS(AQ566<=1,"new",AQ566<=4,"settling",AQ566<=7,"established",AQ566<=12,"stagnant risk",AQ566>12,"highly stagnant")} -> established | AS566: 3 | AT566: {=_xlfn.IFS(AS566<=1,"recently promoted",AS566<=3,"due soon",AS566<=6,"over due",AS566>=7,"critically overdue")} -> due soon | AU566: 6 | AV566: {=_xlfn.IFS(AU566<=1,"new under manager",AU566<=4,"settling",AU566<=8,"established",AU566>=9,"long term")} -> established
A567: 38 | B567: {=_xlfn.IFS(A567<=25,"early career",A567<=35,"mid career",A567<=45,"experienced",A567>=46,"senior")} -> experienced | C567: No | D567: Travel_Frequently | E567: Research & Development | F567: 23 | G567: {=_xlfn.IFS(F567<=5,"very near",F567<=10,"near",F567<=20,"moderate",F567<=29,"far")} -> far | H567: 3 | I567: {=_xlfn.IFS(H567=1,"Below College",H567= 2,"College",H567= 3,"Bachelor",H567= 4,"Master",H567= 5,"Doctor")} -> Bachelor | J567: Life Sciences | K567: 4 | L567: {=_xlfn.IFS(K567=1,"low",K567=2,"medium",K567=3,"high",K567=4,"very high")} -> very high | M567: Male | N567: 2 | O567: {=_xlfn.IFS(N567=1,"low",N567=2,"medium",N567=3,"high",N567=4,"very high")} -> medium | P567: 3 | Q567: {=_xlfn.IFS(P567=1,"junior",P567=2,"mid level",P567=3,"senior",P567=4,"lead",P567=5,"executive")} -> senior | R567: Manufacturing Director | S567: 3 | T567: {=_xlfn.IFS(S567=1,"low",S567=2,"medium",S567=3,"high",S567=4,"very high")} -> high | U567: Single | V567: 9526 | W567: 0 | X567: {=_xlfn.IFS(W567=0,"fresher",W567<=3,"stable",W567<=6,"moderate hopper",W567<=9,"frequent hopper")} -> fresher | Y567: No | Z567: 21 | AA567: {=_xlfn.IFS(Z567<=14,"low hike",Z567<=18,"moderate hike",Z567<=22,"good hike",Z567<=25,"high hike")} -> good hike | AB567: 4 | AC567: {=_xlfn.IFS(AB567=1,"low",AB567=2,"good",AB567=3,"excellent",AB567=4,"outstanding")} -> outstanding | AD567: 2 | AE567: {=_xlfn.IFS(AD567=1,"low",AD567=2,"medium",AD567=3,"high",AD567=4,"very high")} -> medium | AG567: 0 | AH567: {=_xlfn.IFS(AG567=0,"no stock options",AG567=2,"medium",AG567=3,"high",AG567=1,"low")} -> no stock options | AI567: 10 | AJ567: {=_xlfn.IFS(AI567<=2,"fresher",AI567<=7,"early career",AI567<=15,"mid career",AI567<=25,"experienced",AI567>=26,"expert")} -> mid career | AK567: 2 | AL567: {=_xlfn.IFS(AK567=0,"no training",AK567<=2,"low",AK567<=4,"moderate",AK567<=6,"high")} -> low | AM567: 3 | AN567: {=_xlfn.IFS(AM567=1,"low",AM567=2,"medium",AM567=3,"high",AM567=4,"very high")} -> high | AO567: 9 | AP567: {=_xlfn.IFS(AO567<=1,"new",AO567<=5,"early tenure",AO567<=10,"established",AO567<=20,"loyal",AO567>=21,"long term")} -> established | AQ567: 7 | AR567: {=_xlfn.IFS(AQ567<=1,"new",AQ567<=4,"settling",AQ567<=7,"established",AQ567<=12,"stagnant risk",AQ567>12,"highly stagnant")} -> established | AS567: 1 | AT567: {=_xlfn.IFS(AS567<=1,"recently promoted",AS567<=3,"due soon",AS567<=6,"over due",AS567>=7,"critically overdue")} -> recently promoted | AU567: 8 | AV567: {=_xlfn.IFS(AU567<=1,"new under manager",AU567<=4,"settling",AU567<=8,"established",AU567>=9,"long term")} -> established
A568: 36 | B568: {=_xlfn.IFS(A568<=25,"early career",A568<=35,"mid career",A568<=45,"experienced",A568>=46,"senior")} -> experienced | C568: No | D568: Travel_Rarely | E568: Research & Development | F568: 27 | G568: {=_xlfn.IFS(F568<=5,"very near",F568<=10,"near",F568<=20,"moderate",F568<=29,"far")} -> far | H568: 3 | I568: {=_xlfn.IFS(H568=1,"Below College",H568= 2,"College",H568= 3,"Bachelor",H568= 4,"Master",H568= 5,"Doctor")} -> Bachelor | J568: Medical | K568: 3 | L568: {=_xlfn.IFS(K568=1,"low",K568=2,"medium",K568=3,"high",K568=4,"very high")} -> high | M568: Male | N568: 3 | O568: {=_xlfn.IFS(N568=1,"low",N568=2,"medium",N568=3,"high",N568=4,"very high")} -> high | P568: 2 | Q568: {=_xlfn.IFS(P568=1,"junior",P568=2,"mid level",P568=3,"senior",P568=4,"lead",P568=5,"executive")} -> mid level | R568: Healthcare Representative | S568: 3 | T568: {=_xlfn.IFS(S568=1,"low",S568=2,"medium",S568=3,"high",S568=4,"very high")} -> high | U568: Married | V568: 5237 | W568: 6 | X568: {=_xlfn.IFS(W568=0,"fresher",W568<=3,"stable",W568<=6,"moderate hopper",W568<=9,"frequent hopper")} -> moderate hopper | Y568: No | Z568: 13 | AA568: {=_xlfn.IFS(Z568<=14,"low hike",Z568<=18,"moderate hike",Z568<=22,"good hike",Z568<=25,"high hike")} -> low hike | AB568: 3 | AC568: {=_xlfn.IFS(AB568=1,"low",AB568=2,"good",AB568=3,"excellent",AB568=4,"outstanding")} -> excellent | AD568: 2 | AE568: {=_xlfn.IFS(AD568=1,"low",AD568=2,"medium",AD568=3,"high",AD568=4,"very high")} -> medium | AG568: 2 | AH568: {=_xlfn.IFS(AG568=0,"no stock options",AG568=2,"medium",AG568=3,"high",AG568=1,"low")} -> medium | AI568: 17 | AJ568: {=_xlfn.IFS(AI568<=2,"fresher",AI568<=7,"early career",AI568<=15,"mid career",AI568<=25,"experienced",AI568>=26,"expert")} -> experienced | AK568: 3 | AL568: {=_xlfn.IFS(AK568=0,"no training",AK568<=2,"low",AK568<=4,"moderate",AK568<=6,"high")} -> moderate | AM568: 2 | AN568: {=_xlfn.IFS(AM568=1,"low",AM568=2,"medium",AM568=3,"high",AM568=4,"very high")} -> medium | AO568: 7 | AP568: {=_xlfn.IFS(AO568<=1,"new",AO568<=5,"early tenure",AO568<=10,"established",AO568<=20,"loyal",AO568>=21,"long term")} -> established | AQ568: 7 | AR568: {=_xlfn.IFS(AQ568<=1,"new",AQ568<=4,"settling",AQ568<=7,"established",AQ568<=12,"stagnant risk",AQ568>12,"highly stagnant")} -> established | AS568: 7 | AT568: {=_xlfn.IFS(AS568<=1,"recently promoted",AS568<=3,"due soon",AS568<=6,"over due",AS568>=7,"critically overdue")} -> critically overdue | AU568: 7 | AV568: {=_xlfn.IFS(AU568<=1,"new under manager",AU568<=4,"settling",AU568<=8,"established",AU568>=9,"long term")} -> established
A569: 29 | B569: {=_xlfn.IFS(A569<=25,"early career",A569<=35,"mid career",A569<=45,"experienced",A569>=46,"senior")} -> mid career | C569: No | D569: Travel_Rarely | E569: Research & Development | F569: 15 | G569: {=_xlfn.IFS(F569<=5,"very near",F569<=10,"near",F569<=20,"moderate",F569<=29,"far")} -> moderate | H569: 2 | I569: {=_xlfn.IFS(H569=1,"Below College",H569= 2,"College",H569= 3,"Bachelor",H569= 4,"Master",H569= 5,"Doctor")} -> College | J569: Life Sciences | K569: 4 | L569: {=_xlfn.IFS(K569=1,"low",K569=2,"medium",K569=3,"high",K569=4,"very high")} -> very high | M569: Female | N569: 2 | O569: {=_xlfn.IFS(N569=1,"low",N569=2,"medium",N569=3,"high",N569=4,"very high")} -> medium | P569: 2 | Q569: {=_xlfn.IFS(P569=1,"junior",P569=2,"mid level",P569=3,"senior",P569=4,"lead",P569=5,"executive")} -> mid level | R569: Laboratory Technician | S569: 3 | T569: {=_xlfn.IFS(S569=1,"low",S569=2,"medium",S569=3,"high",S569=4,"very high")} -> high | U569: Single | V569: 4193 | W569: 0 | X569: {=_xlfn.IFS(W569=0,"fresher",W569<=3,"stable",W569<=6,"moderate hopper",W569<=9,"frequent hopper")} -> fresher | Y569: Yes | Z569: 12 | AA569: {=_xlfn.IFS(Z569<=14,"low hike",Z569<=18,"moderate hike",Z569<=22,"good hike",Z569<=25,"high hike")} -> low hike | AB569: 3 | AC569: {=_xlfn.IFS(AB569=1,"low",AB569=2,"good",AB569=3,"excellent",AB569=4,"outstanding")} -> excellent | AD569: 4 | AE569: {=_xlfn.IFS(AD569=1,"low",AD569=2,"medium",AD569=3,"high",AD569=4,"very high")} -> very high | AG569: 0 | AH569: {=_xlfn.IFS(AG569=0,"no stock options",AG569=2,"medium",AG569=3,"high",AG569=1,"low")} -> no stock options | AI569: 10 | AJ569: {=_xlfn.IFS(AI569<=2,"fresher",AI569<=7,"early career",AI569<=15,"mid career",AI569<=25,"experienced",AI569>=26,"expert")} -> mid career | AK569: 3 | AL569: {=_xlfn.IFS(AK569=0,"no training",AK569<=2,"low",AK569<=4,"moderate",AK569<=6,"high")} -> moderate | AM569: 3 | AN569: {=_xlfn.IFS(AM569=1,"low",AM569=2,"medium",AM569=3,"high",AM569=4,"very high")} -> high | AO569: 9 | AP569: {=_xlfn.IFS(AO569<=1,"new",AO569<=5,"early tenure",AO569<=10,"established",AO569<=20,"loyal",AO569>=21,"long term")} -> established | AQ569: 5 | AR569: {=_xlfn.IFS(AQ569<=1,"new",AQ569<=4,"settling",AQ569<=7,"established",AQ569<=12,"stagnant risk",AQ569>12,"highly stagnant")} -> established | AS569: 0 | AT569: {=_xlfn.IFS(AS569<=1,"recently promoted",AS569<=3,"due soon",AS569<=6,"over due",AS569>=7,"critically overdue")} -> recently promoted | AU569: 8 | AV569: {=_xlfn.IFS(AU569<=1,"new under manager",AU569<=4,"settling",AU569<=8,"established",AU569>=9,"long term")} -> established
A570: 29 | B570: {=_xlfn.IFS(A570<=25,"early career",A570<=35,"mid career",A570<=45,"experienced",A570>=46,"senior")} -> mid career | C570: No | D570: Travel_Rarely | E570: Research & Development | F570: 21 | G570: {=_xlfn.IFS(F570<=5,"very near",F570<=10,"near",F570<=20,"moderate",F570<=29,"far")} -> far | H570: 4 | I570: {=_xlfn.IFS(H570=1,"Below College",H570= 2,"College",H570= 3,"Bachelor",H570= 4,"Master",H570= 5,"Doctor")} -> Master | J570: Life Sciences | K570: 2 | L570: {=_xlfn.IFS(K570=1,"low",K570=2,"medium",K570=3,"high",K570=4,"very high")} -> medium | M570: Female | N570: 4 | O570: {=_xlfn.IFS(N570=1,"low",N570=2,"medium",N570=3,"high",N570=4,"very high")} -> very high | P570: 3 | Q570: {=_xlfn.IFS(P570=1,"junior",P570=2,"mid level",P570=3,"senior",P570=4,"lead",P570=5,"executive")} -> senior | R570: Manufacturing Director | S570: 1 | T570: {=_xlfn.IFS(S570=1,"low",S570=2,"medium",S570=3,"high",S570=4,"very high")} -> low | U570: Divorced | V570: 9980 | W570: 1 | X570: {=_xlfn.IFS(W570=0,"fresher",W570<=3,"stable",W570<=6,"moderate hopper",W570<=9,"frequent hopper")} -> stable | Y570: No | Z570: 11 | AA570: {=_xlfn.IFS(Z570<=14,"low hike",Z570<=18,"moderate hike",Z570<=22,"good hike",Z570<=25,"high hike")} -> low hike | AB570: 3 | AC570: {=_xlfn.IFS(AB570=1,"low",AB570=2,"good",AB570=3,"excellent",AB570=4,"outstanding")} -> excellent | AD570: 3 | AE570: {=_xlfn.IFS(AD570=1,"low",AD570=2,"medium",AD570=3,"high",AD570=4,"very high")} -> high | AG570: 1 | AH570: {=_xlfn.IFS(AG570=0,"no stock options",AG570=2,"medium",AG570=3,"high",AG570=1,"low")} -> low | AI570: 10 | AJ570: {=_xlfn.IFS(AI570<=2,"fresher",AI570<=7,"early career",AI570<=15,"mid career",AI570<=25,"experienced",AI570>=26,"expert")} -> mid career | AK570: 1 | AL570: {=_xlfn.IFS(AK570=0,"no training",AK570<=2,"low",AK570<=4,"moderate",AK570<=6,"high")} -> low | AM570: 3 | AN570: {=_xlfn.IFS(AM570=1,"low",AM570=2,"medium",AM570=3,"high",AM570=4,"very high")} -> high | AO570: 10 | AP570: {=_xlfn.IFS(AO570<=1,"new",AO570<=5,"early tenure",AO570<=10,"established",AO570<=20,"loyal",AO570>=21,"long term")} -> established | AQ570: 9 | AR570: {=_xlfn.IFS(AQ570<=1,"new",AQ570<=4,"settling",AQ570<=7,"established",AQ570<=12,"stagnant risk",AQ570>12,"highly stagnant")} -> stagnant risk | AS570: 8 | AT570: {=_xlfn.IFS(AS570<=1,"recently promoted",AS570<=3,"due soon",AS570<=6,"over due",AS570>=7,"critically overdue")} -> critically overdue | AU570: 8 | AV570: {=_xlfn.IFS(AU570<=1,"new under manager",AU570<=4,"settling",AU570<=8,"established",AU570>=9,"long term")} -> established
A571: 32 | B571: {=_xlfn.IFS(A571<=25,"early career",A571<=35,"mid career",A571<=45,"experienced",A571>=46,"senior")} -> mid career | C571: No | D571: Travel_Rarely | E571: Research & Development | F571: 5 | G571: {=_xlfn.IFS(F571<=5,"very near",F571<=10,"near",F571<=20,"moderate",F571<=29,"far")} -> very near | H571: 2 | I571: {=_xlfn.IFS(H571=1,"Below College",H571= 2,"College",H571= 3,"Bachelor",H571= 4,"Master",H571= 5,"Doctor")} -> College | J571: Life Sciences | K571: 1 | L571: {=_xlfn.IFS(K571=1,"low",K571=2,"medium",K571=3,"high",K571=4,"very high")} -> low | M571: Male | N571: 4 | O571: {=_xlfn.IFS(N571=1,"low",N571=2,"medium",N571=3,"high",N571=4,"very high")} -> very high | P571: 1 | Q571: {=_xlfn.IFS(P571=1,"junior",P571=2,"mid level",P571=3,"senior",P571=4,"lead",P571=5,"executive")} -> junior | R571: Research Scientist | S571: 2 | T571: {=_xlfn.IFS(S571=1,"low",S571=2,"medium",S571=3,"high",S571=4,"very high")} -> medium | U571: Divorced | V571: 3298 | W571: 0 | X571: {=_xlfn.IFS(W571=0,"fresher",W571<=3,"stable",W571<=6,"moderate hopper",W571<=9,"frequent hopper")} -> fresher | Y571: Yes | Z571: 12 | AA571: {=_xlfn.IFS(Z571<=14,"low hike",Z571<=18,"moderate hike",Z571<=22,"good hike",Z571<=25,"high hike")} -> low hike | AB571: 3 | AC571: {=_xlfn.IFS(AB571=1,"low",AB571=2,"good",AB571=3,"excellent",AB571=4,"outstanding")} -> excellent | AD571: 4 | AE571: {=_xlfn.IFS(AD571=1,"low",AD571=2,"medium",AD571=3,"high",AD571=4,"very high")} -> very high | AG571: 2 | AH571: {=_xlfn.IFS(AG571=0,"no stock options",AG571=2,"medium",AG571=3,"high",AG571=1,"low")} -> medium | AI571: 7 | AJ571: {=_xlfn.IFS(AI571<=2,"fresher",AI571<=7,"early career",AI571<=15,"mid career",AI571<=25,"experienced",AI571>=26,"expert")} -> early career | AK571: 5 | AL571: {=_xlfn.IFS(AK571=0,"no training",AK571<=2,"low",AK571<=4,"moderate",AK571<=6,"high")} -> high | AM571: 2 | AN571: {=_xlfn.IFS(AM571=1,"low",AM571=2,"medium",AM571=3,"high",AM571=4,"very high")} -> medium | AO571: 6 | AP571: {=_xlfn.IFS(AO571<=1,"new",AO571<=5,"early tenure",AO571<=10,"established",AO571<=20,"loyal",AO571>=21,"long term")} -> established | AQ571: 2 | AR571: {=_xlfn.IFS(AQ571<=1,"new",AQ571<=4,"settling",AQ571<=7,"established",AQ571<=12,"stagnant risk",AQ571>12,"highly stagnant")} -> settling | AS571: 0 | AT571: {=_xlfn.IFS(AS571<=1,"recently promoted",AS571<=3,"due soon",AS571<=6,"over due",AS571>=7,"critically overdue")} -> recently promoted | AU571: 5 | AV571: {=_xlfn.IFS(AU571<=1,"new under manager",AU571<=4,"settling",AU571<=8,"established",AU571>=9,"long term")} -> established
A572: 32 | B572: {=_xlfn.IFS(A572<=25,"early career",A572<=35,"mid career",A572<=45,"experienced",A572>=46,"senior")} -> mid career | C572: Yes | D572: Travel_Frequently | E572: Research & Development | F572: 16 | G572: {=_xlfn.IFS(F572<=5,"very near",F572<=10,"near",F572<=20,"moderate",F572<=29,"far")} -> moderate | H572: 1 | I572: {=_xlfn.IFS(H572=1,"Below College",H572= 2,"College",H572= 3,"Bachelor",H572= 4,"Master",H572= 5,"Doctor")} -> Below College | J572: Life Sciences | K572: 2 | L572: {=_xlfn.IFS(K572=1,"low",K572=2,"medium",K572=3,"high",K572=4,"very high")} -> medium | M572: Female | N572: 1 | O572: {=_xlfn.IFS(N572=1,"low",N572=2,"medium",N572=3,"high",N572=4,"very high")} -> low | P572: 1 | Q572: {=_xlfn.IFS(P572=1,"junior",P572=2,"mid level",P572=3,"senior",P572=4,"lead",P572=5,"executive")} -> junior | R572: Research Scientist | S572: 1 | T572: {=_xlfn.IFS(S572=1,"low",S572=2,"medium",S572=3,"high",S572=4,"very high")} -> low | U572: Single | V572: 3919 | W572: 1 | X572: {=_xlfn.IFS(W572=0,"fresher",W572<=3,"stable",W572<=6,"moderate hopper",W572<=9,"frequent hopper")} -> stable | Y572: Yes | Z572: 22 | AA572: {=_xlfn.IFS(Z572<=14,"low hike",Z572<=18,"moderate hike",Z572<=22,"good hike",Z572<=25,"high hike")} -> good hike | AB572: 4 | AC572: {=_xlfn.IFS(AB572=1,"low",AB572=2,"good",AB572=3,"excellent",AB572=4,"outstanding")} -> outstanding | AD572: 2 | AE572: {=_xlfn.IFS(AD572=1,"low",AD572=2,"medium",AD572=3,"high",AD572=4,"very high")} -> medium | AG572: 0 | AH572: {=_xlfn.IFS(AG572=0,"no stock options",AG572=2,"medium",AG572=3,"high",AG572=1,"low")} -> no stock options | AI572: 10 | AJ572: {=_xlfn.IFS(AI572<=2,"fresher",AI572<=7,"early career",AI572<=15,"mid career",AI572<=25,"experienced",AI572>=26,"expert")} -> mid career | AK572: 5 | AL572: {=_xlfn.IFS(AK572=0,"no training",AK572<=2,"low",AK572<=4,"moderate",AK572<=6,"high")} -> high | AM572: 3 | AN572: {=_xlfn.IFS(AM572=1,"low",AM572=2,"medium",AM572=3,"high",AM572=4,"very high")} -> high | AO572: 10 | AP572: {=_xlfn.IFS(AO572<=1,"new",AO572<=5,"early tenure",AO572<=10,"established",AO572<=20,"loyal",AO572>=21,"long term")} -> established | AQ572: 2 | AR572: {=_xlfn.IFS(AQ572<=1,"new",AQ572<=4,"settling",AQ572<=7,"established",AQ572<=12,"stagnant risk",AQ572>12,"highly stagnant")} -> settling | AS572: 6 | AT572: {=_xlfn.IFS(AS572<=1,"recently promoted",AS572<=3,"due soon",AS572<=6,"over due",AS572>=7,"critically overdue")} -> over due | AU572: 7 | AV572: {=_xlfn.IFS(AU572<=1,"new under manager",AU572<=4,"settling",AU572<=8,"established",AU572>=9,"long term")} -> established
A573: 42 | B573: {=_xlfn.IFS(A573<=25,"early career",A573<=35,"mid career",A573<=45,"experienced",A573>=46,"senior")} -> experienced | C573: No | D573: Travel_Rarely | E573: Sales | F573: 8 | G573: {=_xlfn.IFS(F573<=5,"very near",F573<=10,"near",F573<=20,"moderate",F573<=29,"far")} -> near | H573: 4 | I573: {=_xlfn.IFS(H573=1,"Below College",H573= 2,"College",H573= 3,"Bachelor",H573= 4,"Master",H573= 5,"Doctor")} -> Master | J573: Marketing | K573: 3 | L573: {=_xlfn.IFS(K573=1,"low",K573=2,"medium",K573=3,"high",K573=4,"very high")} -> high | M573: Male | N573: 3 | O573: {=_xlfn.IFS(N573=1,"low",N573=2,"medium",N573=3,"high",N573=4,"very high")} -> high | P573: 2 | Q573: {=_xlfn.IFS(P573=1,"junior",P573=2,"mid level",P573=3,"senior",P573=4,"lead",P573=5,"executive")} -> mid level | R573: Sales Executive | S573: 2 | T573: {=_xlfn.IFS(S573=1,"low",S573=2,"medium",S573=3,"high",S573=4,"very high")} -> medium | U573: Married | V573: 6825 | W573: 0 | X573: {=_xlfn.IFS(W573=0,"fresher",W573<=3,"stable",W573<=6,"moderate hopper",W573<=9,"frequent hopper")} -> fresher | Y573: No | Z573: 11 | AA573: {=_xlfn.IFS(Z573<=14,"low hike",Z573<=18,"moderate hike",Z573<=22,"good hike",Z573<=25,"high hike")} -> low hike | AB573: 3 | AC573: {=_xlfn.IFS(AB573=1,"low",AB573=2,"good",AB573=3,"excellent",AB573=4,"outstanding")} -> excellent | AD573: 4 | AE573: {=_xlfn.IFS(AD573=1,"low",AD573=2,"medium",AD573=3,"high",AD573=4,"very high")} -> very high | AG573: 1 | AH573: {=_xlfn.IFS(AG573=0,"no stock options",AG573=2,"medium",AG573=3,"high",AG573=1,"low")} -> low | AI573: 10 | AJ573: {=_xlfn.IFS(AI573<=2,"fresher",AI573<=7,"early career",AI573<=15,"mid career",AI573<=25,"experienced",AI573>=26,"expert")} -> mid career | AK573: 2 | AL573: {=_xlfn.IFS(AK573=0,"no training",AK573<=2,"low",AK573<=4,"moderate",AK573<=6,"high")} -> low | AM573: 3 | AN573: {=_xlfn.IFS(AM573=1,"low",AM573=2,"medium",AM573=3,"high",AM573=4,"very high")} -> high | AO573: 9 | AP573: {=_xlfn.IFS(AO573<=1,"new",AO573<=5,"early tenure",AO573<=10,"established",AO573<=20,"loyal",AO573>=21,"long term")} -> established | AQ573: 7 | AR573: {=_xlfn.IFS(AQ573<=1,"new",AQ573<=4,"settling",AQ573<=7,"established",AQ573<=12,"stagnant risk",AQ573>12,"highly stagnant")} -> established | AS573: 4 | AT573: {=_xlfn.IFS(AS573<=1,"recently promoted",AS573<=3,"due soon",AS573<=6,"over due",AS573>=7,"critically overdue")} -> over due | AU573: 2 | AV573: {=_xlfn.IFS(AU573<=1,"new under manager",AU573<=4,"settling",AU573<=8,"established",AU573>=9,"long term")} -> settling
A574: 30 | B574: {=_xlfn.IFS(A574<=25,"early career",A574<=35,"mid career",A574<=45,"experienced",A574>=46,"senior")} -> mid career | C574: No | D574: Travel_Rarely | E574: Research & Development | F574: 9 | G574: {=_xlfn.IFS(F574<=5,"very near",F574<=10,"near",F574<=20,"moderate",F574<=29,"far")} -> near | H574: 2 | I574: {=_xlfn.IFS(H574=1,"Below College",H574= 2,"College",H574= 3,"Bachelor",H574= 4,"Master",H574= 5,"Doctor")} -> College | J574: Medical | K574: 4 | L574: {=_xlfn.IFS(K574=1,"low",K574=2,"medium",K574=3,"high",K574=4,"very high")} -> very high | M574: Male | N574: 2 | O574: {=_xlfn.IFS(N574=1,"low",N574=2,"medium",N574=3,"high",N574=4,"very high")} -> medium | P574: 1 | Q574: {=_xlfn.IFS(P574=1,"junior",P574=2,"mid level",P574=3,"senior",P574=4,"lead",P574=5,"executive")} -> junior | R574: Laboratory Technician | S574: 3 | T574: {=_xlfn.IFS(S574=1,"low",S574=2,"medium",S574=3,"high",S574=4,"very high")} -> high | U574: Single | V574: 2206 | W574: 1 | X574: {=_xlfn.IFS(W574=0,"fresher",W574<=3,"stable",W574<=6,"moderate hopper",W574<=9,"frequent hopper")} -> stable | Y574: No | Z574: 13 | AA574: {=_xlfn.IFS(Z574<=14,"low hike",Z574<=18,"moderate hike",Z574<=22,"good hike",Z574<=25,"high hike")} -> low hike | AB574: 3 | AC574: {=_xlfn.IFS(AB574=1,"low",AB574=2,"good",AB574=3,"excellent",AB574=4,"outstanding")} -> excellent | AD574: 1 | AE574: {=_xlfn.IFS(AD574=1,"low",AD574=2,"medium",AD574=3,"high",AD574=4,"very high")} -> low | AG574: 0 | AH574: {=_xlfn.IFS(AG574=0,"no stock options",AG574=2,"medium",AG574=3,"high",AG574=1,"low")} -> no stock options | AI574: 10 | AJ574: {=_xlfn.IFS(AI574<=2,"fresher",AI574<=7,"early career",AI574<=15,"mid career",AI574<=25,"experienced",AI574>=26,"expert")} -> mid career | AK574: 5 | AL574: {=_xlfn.IFS(AK574=0,"no training",AK574<=2,"low",AK574<=4,"moderate",AK574<=6,"high")} -> high | AM574: 3 | AN574: {=_xlfn.IFS(AM574=1,"low",AM574=2,"medium",AM574=3,"high",AM574=4,"very high")} -> high | AO574: 10 | AP574: {=_xlfn.IFS(AO574<=1,"new",AO574<=5,"early tenure",AO574<=10,"established",AO574<=20,"loyal",AO574>=21,"long term")} -> established | AQ574: 0 | AR574: {=_xlfn.IFS(AQ574<=1,"new",AQ574<=4,"settling",AQ574<=7,"established",AQ574<=12,"stagnant risk",AQ574>12,"highly stagnant")} -> new | AS574: 1 | AT574: {=_xlfn.IFS(AS574<=1,"recently promoted",AS574<=3,"due soon",AS574<=6,"over due",AS574>=7,"critically overdue")} -> recently promoted | AU574: 8 | AV574: {=_xlfn.IFS(AU574<=1,"new under manager",AU574<=4,"settling",AU574<=8,"established",AU574>=9,"long term")} -> established
A575: 27 | B575: {=_xlfn.IFS(A575<=25,"early career",A575<=35,"mid career",A575<=45,"experienced",A575>=46,"senior")} -> mid career | C575: No | D575: Travel_Frequently | E575: Sales | F575: 8 | G575: {=_xlfn.IFS(F575<=5,"very near",F575<=10,"near",F575<=20,"moderate",F575<=29,"far")} -> near | H575: 3 | I575: {=_xlfn.IFS(H575=1,"Below College",H575= 2,"College",H575= 3,"Bachelor",H575= 4,"Master",H575= 5,"Doctor")} -> Bachelor | J575: Life Sciences | K575: 4 | L575: {=_xlfn.IFS(K575=1,"low",K575=2,"medium",K575=3,"high",K575=4,"very high")} -> very high | M575: Male | N575: 3 | O575: {=_xlfn.IFS(N575=1,"low",N575=2,"medium",N575=3,"high",N575=4,"very high")} -> high | P575: 3 | Q575: {=_xlfn.IFS(P575=1,"junior",P575=2,"mid level",P575=3,"senior",P575=4,"lead",P575=5,"executive")} -> senior | R575: Sales Executive | S575: 3 | T575: {=_xlfn.IFS(S575=1,"low",S575=2,"medium",S575=3,"high",S575=4,"very high")} -> high | U575: Single | V575: 8726 | W575: 1 | X575: {=_xlfn.IFS(W575=0,"fresher",W575<=3,"stable",W575<=6,"moderate hopper",W575<=9,"frequent hopper")} -> stable | Y575: No | Z575: 15 | AA575: {=_xlfn.IFS(Z575<=14,"low hike",Z575<=18,"moderate hike",Z575<=22,"good hike",Z575<=25,"high hike")} -> moderate hike | AB575: 3 | AC575: {=_xlfn.IFS(AB575=1,"low",AB575=2,"good",AB575=3,"excellent",AB575=4,"outstanding")} -> excellent | AD575: 4 | AE575: {=_xlfn.IFS(AD575=1,"low",AD575=2,"medium",AD575=3,"high",AD575=4,"very high")} -> very high | AG575: 0 | AH575: {=_xlfn.IFS(AG575=0,"no stock options",AG575=2,"medium",AG575=3,"high",AG575=1,"low")} -> no stock options | AI575: 9 | AJ575: {=_xlfn.IFS(AI575<=2,"fresher",AI575<=7,"early career",AI575<=15,"mid career",AI575<=25,"experienced",AI575>=26,"expert")} -> mid career | AK575: 0 | AL575: {=_xlfn.IFS(AK575=0,"no training",AK575<=2,"low",AK575<=4,"moderate",AK575<=6,"high")} -> no training | AM575: 3 | AN575: {=_xlfn.IFS(AM575=1,"low",AM575=2,"medium",AM575=3,"high",AM575=4,"very high")} -> high | AO575: 9 | AP575: {=_xlfn.IFS(AO575<=1,"new",AO575<=5,"early tenure",AO575<=10,"established",AO575<=20,"loyal",AO575>=21,"long term")} -> established | AQ575: 8 | AR575: {=_xlfn.IFS(AQ575<=1,"new",AQ575<=4,"settling",AQ575<=7,"established",AQ575<=12,"stagnant risk",AQ575>12,"highly stagnant")} -> stagnant risk | AS575: 1 | AT575: {=_xlfn.IFS(AS575<=1,"recently promoted",AS575<=3,"due soon",AS575<=6,"over due",AS575>=7,"critically overdue")} -> recently promoted | AU575: 7 | AV575: {=_xlfn.IFS(AU575<=1,"new under manager",AU575<=4,"settling",AU575<=8,"established",AU575>=9,"long term")} -> established
... A1471: 23 | B1471: {=_xlfn.IFS(A1471<=25,"early career",A1471<=35,"mid career",A1471<=45,"experienced",A1471>=46,"senior")} -> early career | C1471: Yes | D1471: Travel_Frequently | E1471: Sales | F1471: 9 | G1471: {=_xlfn.IFS(F1471<=5,"very near",F1471<=10,"near",F1471<=20,"moderate",F1471<=29,"far")} -> near | H1471: 3 | I1471: {=_xlfn.IFS(H1471=1,"Below College",H1471= 2,"College",H1471= 3,"Bachelor",H1471= 4,"Master",H1471= 5,"Doctor")} -> Bachelor | J1471: Marketing | K1471: 4 | L1471: {=_xlfn.IFS(K1471=1,"low",K1471=2,"medium",K1471=3,"high",K1471=4,"very high")} -> very high | M1471: Male | N1471: 3 | O1471: {=_xlfn.IFS(N1471=1,"low",N1471=2,"medium",N1471=3,"high",N1471=4,"very high")} -> high | P1471: 1 | Q1471: {=_xlfn.IFS(P1471=1,"junior",P1471=2,"mid level",P1471=3,"senior",P1471=4,"lead",P1471=5,"executive")} -> junior | R1471: Sales Representative | S1471: 1 | T1471: {=_xlfn.IFS(S1471=1,"low",S1471=2,"medium",S1471=3,"high",S1471=4,"very high")} -> low | U1471: Married | V1471: 1790 | W1471: 1 | X1471: {=_xlfn.IFS(W1471=0,"fresher",W1471<=3,"stable",W1471<=6,"moderate hopper",W1471<=9,"frequent hopper")} -> stable | Y1471: No | Z1471: 19 | AA1471: {=_xlfn.IFS(Z1471<=14,"low hike",Z1471<=18,"moderate hike",Z1471<=22,"good hike",Z1471<=25,"high hike")} -> good hike | AB1471: 3 | AC1471: {=_xlfn.IFS(AB1471=1,"low",AB1471=2,"good",AB1471=3,"excellent",AB1471=4,"outstanding")} -> excellent | AD1471: 1 | AE1471: {=_xlfn.IFS(AD1471=1,"low",AD1471=2,"medium",AD1471=3,"high",AD1471=4,"very high")} -> low | AG1471: 1 | AH1471: {=_xlfn.IFS(AG1471=0,"no stock options",AG1471=2,"medium",AG1471=3,"high",AG1471=1,"low")} -> low | AI1471: 1 | AJ1471: {=_xlfn.IFS(AI1471<=2,"fresher",AI1471<=7,"early career",AI1471<=15,"mid career",AI1471<=25,"experienced",AI1471>=26,"expert")} -> fresher | AK1471: 3 | AL1471: {=_xlfn.IFS(AK1471=0,"no training",AK1471<=2,"low",AK1471<=4,"moderate",AK1471<=6,"high")} -> moderate | AM1471: 2 | AN1471: {=_xlfn.IFS(AM1471=1,"low",AM1471=2,"medium",AM1471=3,"high",AM1471=4,"very high")} -> medium | AO1471: 1 | AP1471: {=_xlfn.IFS(AO1471<=1,"new",AO1471<=5,"early tenure",AO1471<=10,"established",AO1471<=20,"loyal",AO1471>=21,"long term")} -> new | AQ1471: 0 | AR1471: {=_xlfn.IFS(AQ1471<=1,"new",AQ1471<=4,"settling",AQ1471<=7,"established",AQ1471<=12,"stagnant risk",AQ1471>12,"highly stagnant")} -> new | AS1471: 1 | AT1471: {=_xlfn.IFS(AS1471<=1,"recently promoted",AS1471<=3,"due soon",AS1471<=6,"over due",AS1471>=7,"critically overdue")} -> recently promoted | AU1471: 0 | AV1471: {=_xlfn.IFS(AU1471<=1,"new under manager",AU1471<=4,"settling",AU1471<=8,"established",AU1471>=9,"long term")} -> new under manager
A1472: =AVERAGE(A2:A1471) -> 36.92381 | B1472: =COUNTA(B2:B1471) -> 1470 | K1472: =AVERAGE(K2:K1471) -> 2.7217687

Sheet pivot tables
A1: DONE
A2: Count of Attrition | B2: Attrition
A3: Age-group | B3: No | C3: Yes | D3: Grand Total
A4: 1.early career | B4: 79 | C4: 44 | D4: 123 | E4: =ROUND(C4/D4*100,1)&"%" -> 35.8% | H4: AGE GROUP | I4: ATTRITION RATE
A5: 2.mid career | B5: 490 | C5: 116 | D5: 606 | E5: =ROUND(C5/D5*100,1)&"%" -> 19.1% | F5: EALRY CAREER TENDS TO RESIGN MORE - MORE FOCUS ON ONBOARDING AND GROWTH OPUURTUNITIES | H5: =MID(A4,3,LEN(A4)) -> early career | I5: 35.8
A6: 3.experienced | B6: 425 | C6: 43 | D6: 468 | E6: =ROUND(C6/D6*100,1)&"%" -> 9.2% | H6: =MID(A5,3,LEN(A5)) -> mid career | I6: 19.1
A7: 4.senior | B7: 239 | C7: 34 | D7: 273 | E7: =ROUND(C7/D7*100,1)&"%" -> 12.5% | H7: =MID(A6,3,LEN(A6)) -> experienced | I7: 9.2
A8: Grand Total | B8: 1233 | C8: 237 | D8: 1470 | H8: =MID(A7,3,LEN(A7)) -> senior | I8: 12.5
A14: DONE
A15: Count of Attrition | B15: Attrition
A16: BusinessTravel | B16: No | C16: Yes | D16: Grand Total | H16: BusinessTravel | I16: attrition rate
A17: Non-Travel | B17: 138 | C17: 12 | D17: 150 | E17: =C17/D17*100 -> 8 | H17: Non-Travel | I17: 8
A18: Travel_Frequently | B18: 208 | C18: 69 | D18: 277 | E18: =C18/D18*100 -> 24.909747 | G18: FREQ TRAVELLERS TEND TO RESIGN MORE | H18: Travel_Rarely | I18: 14.95
A19: Travel_Rarely | B19: 887 | C19: 156 | D19: 1043 | E19: =C19/D19*100 -> 14.956855 | G19: MAKE TRAVELS MORE ENJOYABLE | H19: Travel_Frequently | I19: 24.9
A20: Grand Total | B20: 1233 | C20: 237 | D20: 1470
A23: DONE
A24: Count of Attrition | B24: Attrition
A25: Department | B25: No | C25: Yes | D25: Grand Total
A26: Human Resources | B26: 51 | C26: 12 | D26: 63 | E26: =C26/D26*100 -> 19.047619
A27: Research & Development | B27: 828 | C27: 133 | D27: 961 | E27: =C27/D27*100 -> 13.83975 | G27: check for target pressures | H27: Department | I27: attrition rate
A28: Sales | B28: 354 | C28: 92 | D28: 446 | E28: =C28/D28*100 -> 20.627803 | H28: Research & Development | I28: 13.83
A29: Grand Total | B29: 1233 | C29: 237 | D29: 1470 | H29: Human Resources | I29: 19.04
H30: Sales | I30: 20.62
A32: DONE
A33: Count of Attrition | B33: Attrition
A34: DistanceFromHome2 | B34: No | C34: Yes | D34: Grand Total
A35: far | B35: 159 | C35: 45 | D35: 204 | E35: =C35/D35*100 -> 22.058824
A36: moderate | B36: 192 | C36: 48 | D36: 240 | E36: =C36/D36*100 -> 20 | G36: expected | I36: DistanceFromHome2 | J36: TrainingTimesLastYear2 | K36: work life balance
A37: near | B37: 337 | C37: 57 | D37: 394 | E37: =C37/D37*100 -> 14.467005 | G37: company provided stays | H37: 1 | I37: 13.8 | J37: 27.8 | K37: 31.3
A38: very near | B38: 545 | C38: 87 | D38: 632 | E38: =C38/D38*100 -> 13.765823 | H38: 2 | I38: 14.5 | J38: 17.3 | K38: 16.9
A39: Grand Total | B39: 1233 | C39: 237 | D39: 1470 | H39: 3 | I39: 20 | J39: 15.5 | K39: 14.2
H40: 4 | I40: 22.1 | J40: 10.9 | K40: 17.6
A42: DONE
A43: Count of Attrition | B43: Attrition
A44: EducationField | B44: No | C44: Yes | D44: Grand Total
A45: Human Resources | B45: 20 | C45: 7 | D45: 27 | E45: =C45/D45*100 -> 25.925926 | G45: why ? | H45: EducationField | I45: attrition
A46: Life Sciences | B46: 517 | C46: 89 | D46: 606 | E46: =C46/D46*100 -> 14.686469 | H46: Other | I46: 13.4
A47: Marketing | B47: 124 | C47: 35 | D47: 159 | E47: =C47/D47*100 -> 22.012579 | H47: Medical | I47: 13.6
A48: Medical | B48: 401 | C48: 63 | D48: 464 | E48: =C48/D48*100 -> 13.577586 | H48: Life Sciences | I48: 14.7
A49: Other | B49: 71 | C49: 11 | D49: 82 | E49: =C49/D49*100 -> 13.414634 | H49: Marketing | I49: 22
A50: Technical Degree | B50: 100 | C50: 32 | D50: 132 | E50: =C50/D50*100 -> 24.242424 | H50: Technical Degree | I50: 24.2
A51: Grand Total | B51: 1233 | C51: 237 | D51: 1470 | H51: Human Resources | I51: 25.9
A54: DONE
A55: Count of Attrition | B55: Attrition | H55: Gender | I55: attrition
A56: Gender | B56: No | C56: Yes | D56: Grand Total | H56: Female | I56: 14.795918
A57: Female | B57: 501 | C57: 87 | D57: 588 | E57: =C57/D57*100 -> 14.795918 | H57: Male | I57: 17.006803
A58: Male | B58: 732 | C58: 150 | D58: 882 | E58: =C58/D58*100 -> 17.006803
A59: Grand Total | B59: 1233 | C59: 237 | D59: 1470
A61: DONE
A62: Count of Attrition | B62: Attrition
A63: JobLevel2 | B63: No | C63: Yes | D63: Grand Total | H63: JobLevel2 | I63: attrition
A64: 1.junior | B64: 400 | C64: 143 | D64: 543 | E64: =C64/D64*100 -> 26.335175 | G64: 143 | H64: =_xlfn.TEXTAFTER(A64,".") -> junior | I64: =ROUND(E64,1) -> 26.3
A65: 2.mid level | B65: 482 | C65: 52 | D65: 534 | E65: =C65/D65*100 -> 9.7378277 | F65: why ? | G65: 52 | H65: =_xlfn.TEXTAFTER(A65,".") -> mid level | I65: =ROUND(E65,1) -> 9.7
A66: 3.senior | B66: 186 | C66: 32 | D66: 218 | E66: =C66/D66*100 -> 14.678899 | G66: 32 | H66: =_xlfn.TEXTAFTER(A66,".") -> senior | I66: =ROUND(E66,1) -> 14.7
A67: 4.lead | B67: 101 | C67: 5 | D67: 106 | E67: =C67/D67*100 -> 4.7169811 | G67: 5 | H67: =_xlfn.TEXTAFTER(A67,".") -> lead | I67: =ROUND(E67,1) -> 4.7
A68: 5.executive | B68: 64 | C68: 5 | D68: 69 | E68: =C68/D68*100 -> 7.2463768 | G68: 5 | H68: =_xlfn.TEXTAFTER(A68,".") -> executive | I68: =ROUND(E68,1) -> 7.2
A69: Grand Total | B69: 1233 | C69: 237 | D69: 1470
A72: DONE
A73: Count of Attrition | B73: Attrition
A74: JobRole | B74: No | C74: Yes | D74: Grand Total | H74: JobRole | I74: Column1
A75: Healthcare Representative | B75: 122 | C75: 9 | D75: 131 | E75: =C75/D75*100 -> 6.870229 | H75: Research Director | I75: 2.5
A76: Human Resources | B76: 40 | C76: 12 | D76: 52 | E76: =C76/D76*100 -> 23.076923 | F76: highest | H76: Manager | I76: 4.9
A77: Laboratory Technician | B77: 197 | C77: 62 | D77: 259 | E77: =C77/D77*100 -> 23.938224 | H77: Healthcare Representative | I77: 6.9
A78: Manager | B78: 97 | C78: 5 | D78: 102 | E78: =C78/D78*100 -> 4.9019608 | H78: Manufacturing Director | I78: 6.9
A79: Manufacturing Director | B79: 135 | C79: 10 | D79: 145 | E79: =C79/D79*100 -> 6.8965517 | H79: Research Scientist | I79: 16.1
A80: Research Director | B80: 78 | C80: 2 | D80: 80 | E80: =C80/D80*100 -> 2.5 | H80: Sales Executive | I80: 17.5
A81: Research Scientist | B81: 245 | C81: 47 | D81: 292 | E81: =C81/D81*100 -> 16.09589 | H81: Human Resources | I81: 23.1
A82: Sales Executive | B82: 269 | C82: 57 | D82: 326 | E82: =C82/D82*100 -> 17.484663 | H82: Laboratory Technician | I82: 23.9
A83: Sales Representative | B83: 50 | C83: 33 | D83: 83 | E83: =C83/D83*100 -> 39.759036 | H83: Sales Representative | I83: 39.8
A84: Grand Total | B84: 1233 | C84: 237 | D84: 1470
A87: DONE
A88: Count of Attrition | B88: Attrition | H88: MaritalStatus | I88: Column1
A89: MaritalStatus | B89: No | C89: Yes | D89: Grand Total | H89: Divorced | I89: 10.091743
A90: Divorced | B90: 294 | C90: 33 | D90: 327 | E90: =C90/D90*100 -> 10.091743 | H90: Married | I90: 12.481426
A91: Married | B91: 589 | C91: 84 | D91: 673 | E91: =C91/D91*100 -> 12.481426 | H91: Single | I91: 25.531915
A92: Single | B92: 350 | C92: 120 | D92: 470 | E92: =C92/D92*100 -> 25.531915
A93: Grand Total | B93: 1233 | C93: 237 | D93: 1470
A96: Count of Attrition | B96: Attrition | H96: OverTime | I96: Column1
A97: OverTime | B97: No | C97: Yes | D97: Grand Total | H97: No | I97: 10.4
A98: No | B98: 944 | C98: 110 | D98: 1054 | E98: =C98/D98*100 -> 10.436433 | H98: Yes | I98: 30.5
A99: Yes | B99: 289 | C99: 127 | D99: 416 | E99: =C99/D99*100 -> 30.528846
A100: Grand Total | B100: 1233 | C100: 237 | D100: 1470 | I100: =ROUND(I97,1) -> 10.4
I101: =ROUND(I98,1) -> 30.5
A102: DONE
A103: Count of Attrition | B103: Attrition
A104: StockOptionLevel2 | B104: No | C104: Yes | D104: Grand Total | H104: StockOptionLevel2 | I104: Column1
A105: 4.high | B105: 70 | C105: 15 | D105: 85 | E105: =C105/D105*100 -> 17.647059 | H105: =_xlfn.TEXTAFTER(A105,".") -> high | I105: =ROUND(E105,1) -> 17.6
A106: 3.medium | B106: 146 | C106: 12 | D106: 158 | E106: =C106/D106*100 -> 7.5949367 | H106: =_xlfn.TEXTAFTER(A106,".") -> medium | I106: =ROUND(E106,1) -> 7.6
A107: 2.low | B107: 540 | C107: 56 | D107: 596 | E107: =C107/D107*100 -> 9.3959732 | F107: ??? | H107: =_xlfn.TEXTAFTER(A107,".") -> low | I107: =ROUND(E107,1) -> 9.4
A108: 1.no stock | B108: 477 | C108: 154 | D108: 631 | E108: =C108/D108*100 -> 24.405705 | H108: =_xlfn.TEXTAFTER(A108,".") -> no stock | I108: =ROUND(E108,1) -> 24.4
A109: Grand Total | B109: 1233 | C109: 237 | D109: 1470
A111: DONE
A112: Count of Attrition | B112: Attrition | H112: TotalWorkingYears2 | I112: Column1
A113: TotalWorkingYears2 | B113: No | C113: Yes | D113: Grand Total | H113: expert | I113: 7.1428571
A114: early career | B114: 322 | C114: 77 | D114: 399 | E114: =C114/D114*100 -> 19.298246 | H114: experienced | I114: 9.3023256
A115: experienced | B115: 234 | C115: 24 | D115: 258 | E115: =C115/D115*100 -> 9.3023256 | H115: mid career | I115: 12.668919
A116: expert | B116: 91 | C116: 7 | D116: 98 | E116: =C116/D116*100 -> 7.1428571 | H116: early career | I116: 19.298246
A117: fresher | B117: 69 | C117: 54 | D117: 123 | E117: =C117/D117*100 -> 43.902439 | F117: highest | H117: fresher | I117: 43.902439
A118: mid career | B118: 517 | C118: 75 | D118: 592 | E118: =C118/D118*100 -> 12.668919
A119: Grand Total | B119: 1233 | C119: 237 | D119: 1470
...

Sheet dashboard
B1: IBM - EMPLOYEE ATTRITION DASHBOARD
B4: NO.OF VARIABLES | D4: NO.OF DEPARTMENTS | F4: ATTRITION RATE | H4: ATTRITION | J4: TOTAL EMPLOYEES | M4: AVG. SALARY AT EXIT | P4: AVG. SATISFACTION AT EXIT | S4: AVG.TENURE AT EXIT | U4: AVG. AGE AT EXIT
B5: 27 | D5: 3 | F5: =ROUND(H5/J5*100,0)&"%" -> 16% | H5: =COUNTIF(data!C2:C1471,"Yes") -> 237 | J5: =COUNTA(data!B2:B1471) -> 1470 | M5: ="$"&ROUND(AVERAGEIF(data!C2:C1471,"Yes",data!V2:V1471),0) -> $4787 | P5: =ROUND(AVERAGEIF(data!C2:C1471,"Yes",data!S2:S1471),0)&"/4" -> 2/4 | S5: =ROUND(AVERAGEIF(data!C2:C1471,"Yes",data!AO2:AO1471),0) -> 5 | U5: =ROUND(AVERAGEIF(data!C2:C1471,"Yes",data!A2:A1471),0) -> 34

Sheet insights and recommendations 
B2: FINAL PROJECT SUMMARY
B5: BUSINESS PROBLEM
B6: The company is experiencing a 16% attrition rate, losing 237 employees — above industry benchmark. The goal was to identify which employee segments are most at risk and recommend data-driven retention strategies.
B8: INSIGHTS
B9: Overtime is the #1 attrition driver — 30.5% of overtime workers leave
B10: Sales Representatives are the most vulnerable role at 39.8%
B11: Early Career employees leave at 35.8% — nearly 4x senior staff
B12: No stock options correlates with 24.4% attrition
B13: Frequent travellers show 3x attrition of non-travellers
B14: The typical exiting employee is 34 years old, 5 years tenure, earning $4,787/month
B15: RECOMMENDATIONS
B16: Implement overtime policy — cap mandatory overtime, introduce compensation or comp-off for overtime workers
... B21: Mandatory promotion review at 3 years — no employee should wait beyond 3 years without formal assessment
